Workbook
Name AMF12M: OFFSET('[1]LR charts'!$AI$116,0,0,COUNT('[1]LR charts'!$AI$1:$AI$65536)-109,1)
Name AMF5YR: OFFSET('[1]LR charts'!$AI$67,0,0,COUNT('[1]LR charts'!$AI$1:$AI$65536)-60,1)
Name cost: #REF!
Name cost: #REF!
Name cost: #REF!
Name cost: #REF!
Name date: #REF!
Name date: #REF!
Name date: #REF!
Name date: #REF!
Name LacEth: #REF!
Name LacEth: #REF!
Name LacEth: #REF!
Name LacEth: #REF!
Name MilkpermBS: #REF!
Name MilkpermBS: #REF!
Name MilkpermBS: #REF!
Name MilkpermBS: #REF!
Name MilkpermCas: #REF!
Name MilkpermCas: #REF!
Name MilkpermCas: #REF!
Name MilkpermCas: #REF!
Name MilkpermDS: #REF!
Name MilkpermDS: #REF!
Name MilkpermDS: #REF!
Name MilkpermDS: #REF!
Name MilkpermLC: #REF!
Name MilkpermLC: #REF!
Name MilkpermLC: #REF!
Name MilkpermLC: #REF!
Name milkpermMPC70: #REF!
Name milkpermMPC70: #REF!
Name milkpermMPC70: #REF!
Name milkpermMPC70: #REF!
Name MilkpermRC: #REF!
Name MilkpermRC: #REF!
Name MilkpermRC: #REF!
Name MilkpermRC: #REF!
Name SMP12M: OFFSET('[1]LR charts'!$AL$116,0,0,COUNT('[1]LR charts'!$AL$1:$AL$65536)-109,1)
Name SMP5Yr: OFFSET('[1]LR charts'!$AL$67,0,0,COUNT('[1]LR charts'!$AL$1:$AL$65536)-60,1)
Name WMP5Yr: OFFSET('[1]LR charts'!$AN$67,0,0,COUNT('[1]LR charts'!$AN$1:$AN$65536)-60,1)
Name WMPGraph: OFFSET('[1]LR charts'!$AN$67,0,0,COUNT('[1]LR charts'!$AN$1:$AN$65536)-60,1)

Sheet BMC and Milk Procurement
E1: 2011-12 | F1: 2012-13 | G1: 2013-14 | H1: 2014-15 | I1: 2015-16 | J1: 2016-17 | K1: 2017-18 | L1: 2018-19 | M1: 2019-20 | N1: 2020-21 | O1: 2021-22 | P1: 2022-23 | Q1: 2023-24 | R1: 2024-25 | S1: 2025-26 | T1: 2026-27 | U1: 2027-28 | V1: 2028-29 | W1: 2029-30 | X1: 2030-31 | Y1: 2031-32 | Z1: 2032-33 | AA1: 2033-34 | AB1: 2034-35 | AC1: 2036-37
A2: Operating Expense
A3: Bull Production-PT | B3: Million Rupees | E3: 95.81198 | F3: 113.36445 | G3: 130.45873 | H3: 145.31488 | I3: 153.27316 | J3: 164.78352 | K3: =J3 -> 164.78352 | L3: =K3 -> 164.78352 | M3: =L3 -> 164.78352 | N3: =M3 -> 164.78352 | O3: =N3 -> 164.78352 | P3: =O3 -> 164.78352 | Q3: =P3 -> 164.78352 | R3: =Q3 -> 164.78352 | ... AC3: =AB3 -> 164.78352
A4: Breed Improvement | B4: Million Rupees | E4: 20.44365 | F4: 36.39845 | G4: 40.498876 | H4: 44.048538 | I4: 44.91477 | J4: 46.565408 | K4: =J4 -> 46.565408 | L4: =K4 -> 46.565408 | M4: =L4 -> 46.565408 | N4: =M4 -> 46.565408 | O4: =N4 -> 46.565408 | P4: =O4 -> 46.565408 | Q4: =P4 -> 46.565408 | R4: =Q4 -> 46.565408 | ... AC4: =AB4 -> 46.565408
A5: Semen Production | B5: Million Rupees | E5: =SUM(E6:E7) -> 55.197528 | F5: =SUM(F6:F7) -> 121.06552 | G5: =SUM(G6:G7) -> 132.84173 | H5: =SUM(H6:H7) -> 135.88708 | I5: =SUM(I6:I7) -> 140.82006 | J5: =SUM(J6:J7) -> 148.75277 | K5: =SUM(K6:K7) -> 157.36785 | L5: =SUM(L6:L7) -> 162.80511 | ... AC5: =SUM(AC6:AC7) -> 163.69464
A6: Training: Strengthening SS | B6: Million Rupees | E6: 0 | F6: 5.9555556 | G6: 5.9555556 | H6: 0 | I6: 0 | J6: 0
A7: New Semen Stations | B7: Million Rupees | E7: =SUM(E82:E85) -> 55.197528 | F7: =SUM(F82:F85) -> 115.10997 | G7: =SUM(G82:G85) -> 126.88618 | H7: =SUM(H82:H85) -> 135.88708 | I7: =SUM(I82:I85) -> 140.82006 | J7: =SUM(J82:J85) -> 148.75277 | K7: =SUM(K82:K85) -> 157.36785 | L7: =SUM(L82:L85) -> 162.80511 | ... AC7: =SUM(AC82:AC85) -> 163.69464
A8: Import of Bulls | B8: Million Rupees | E8: 111.11111 | F8: 111.11111 | G8: 0 | H8: 111.11111 | I8: 0 | J8: 111.11111 | K8: 0 | L8: 0 | M8: 0 | N8: 0 | O8: 0 | P8: 0 | Q8: 0 | R8: 0 | S8: 0 | T8: 0 | U8: 0 | V8: 0 | W8: 0 | X8: 0 | Y8: 0 | Z8: 0 | AA8: 0 | AB8: 0 | AC8: 0
A9: AI Delivery | B9: Million Rupees | E9: 131.646 | F9: 417.1645 | G9: 786.7945 | H9: 611.0008 | I9: 589.5436 | J9: 569.138 | K9: =J9 -> 569.138 | L9: =K9 -> 569.138 | M9: =L9 -> 569.138 | N9: =M9 -> 569.138 | O9: =N9 -> 569.138 | P9: =O9 -> 569.138 | Q9: =P9 -> 569.138 | R9: =Q9 -> 569.138 | ... AC9: =AB9 -> 569.138
A10: LN Delivery | B10: Million Rupees | E10: 0 | F10: 0.04908 | G10: 0.04499 | H10: 0.04499 | I10: 0.01636 | J10: 0 | K10: 0 | L10: 0 | M10: 0 | N10: 0 | O10: 0 | P10: 0 | Q10: 0 | R10: 0 | S10: 0 | T10: 0 | U10: 0 | V10: 0 | W10: 0 | X10: 0 | Y10: 0 | Z10: 0 | AA10: 0 | AB10: 0 | AC10: 0
A11: Information system | B11: Million Rupees | E11: 23.57 | F11: 23.626 | G11: 23.579 | H11: 23.524 | I11: 23.413 | J11: 23.413 | K11: 0 | L11: =K11 -> 0 | M11: =L11 -> 0 | N11: =M11 -> 0 | O11: =N11 -> 0 | P11: =O11 -> 0 | Q11: =P11 -> 0 | R11: =Q11 -> 0 | S11: =R11 -> 0 | ... AC11: =AB11 -> 0
A12: Animal Health | B12: Million Rupees | E12: 0 | F12: 0 | G12: 0 | H12: 0 | I12: 0 | J12: 0 | K12: 0 | L12: =K12 -> 0 | M12: =L12 -> 0 | N12: =M12 -> 0 | O12: =N12 -> 0 | P12: =O12 -> 0 | Q12: =P12 -> 0 | R12: =Q12 -> 0 | S12: =R12 -> 0 | ... AC12: =AB12 -> 0
A13: Heifer Rearing | B13: Million Rupees | E13: 12.272 | F13: 22.012 | G13: 31.312 | H13: 15.26 | I13: 11.36 | J13: 11.36 | K13: =J13 -> 11.36 | L13: =K13 -> 11.36 | M13: =L13 -> 11.36 | N13: =M13 -> 11.36 | O13: =N13 -> 11.36 | P13: =O13 -> 11.36 | Q13: =P13 -> 11.36 | R13: =Q13 -> 11.36 | ... AC13: =AB13 -> 11.36
A14: RBP | B14: Million Rupees | E14: =E92 -> 154.64111 | F14: =F92 -> 417.66303 | G14: =G92 -> 642.83917 | H14: =H92 -> 690.5323 | I14: =I92 -> 575.68596 | J14: =J92 -> 268.88586 | K14: =K92 -> 268.88586 | L14: =L92 -> 268.88586 | ... AC14: =AC92 -> 268.88586
A15: Fodder Development | B15: Million Rupees | E15: 35.27 | F15: 152.579 | G15: 180.596 | H15: 268.4195 | I15: 282.0975 | J15: 290.551 | K15: =J15 -> 290.551 | L15: =K15 -> 290.551 | M15: =L15 -> 290.551 | N15: =M15 -> 290.551 | O15: =N15 -> 290.551 | P15: =O15 -> 290.551 | Q15: =P15 -> 290.551 | R15: =Q15 -> 290.551 | ... AC15: =AB15 -> 290.551
A16: Milk Collection and Bulking | B16: Million Rupees | E16: =E108 -> #REF! | F16: =F108 -> #REF! | G16: =G108 -> #REF! | H16: =H108 -> #REF! | I16: =I108 -> #REF! | J16: =J108 -> #REF! | K16: =K108 -> #REF! | L16: =L108 -> #REF! | ... AC16: =AC108 -> #REF!
A17: Total Incremental Costs | B17: Million Rupees | E17: =SUM(E3,E4,E5,E8,E9,E10,E11,E12,E13,E14,E15,E16) -> #REF! | F17: =SUM(F3,F4,F5,F8,F9,F10,F11,F12,F13,F14,F15,F16) -> #REF! | G17: =SUM(G3,G4,G5,G8,G9,G10,G11,G12,G13,G14,G15,G16) -> #REF! | H17: =SUM(H3,H4,H5,H8,H9,H10,H11,H12,H13,H14,H15,H16) -> #REF! | I17: =SUM(I3,I4,I5,I8,I9,I10,I11,I12,I13,I14,I15,I16) -> #REF! | J17: =SUM(J3,J4,J5,J8,J9,J10,J11,J12,J13,J14,J15,J16) -> #REF! | K17: =SUM(K3,K4,K5,K8,K9,K10,K11,K12,K13,K14,K15,K16) -> #REF! | L17: =SUM(L3,L4,L5,L8,L9,L10,L11,L12,L13,L14,L15,L16) -> #REF! | ... AC17: =SUM(AC3,AC4,AC5,AC8,AC9,AC10,AC11,AC12,AC13,AC14,AC15,AC16) -> #REF!
A20: CAPITAL INVESTMENT
A23: Bull Production through PT | B23: Million Rupees | C23: 1 | E23: 119.185 | F23: 34.7 | G23: 11.559 | H23: 14.411 | I23: 10.457 | J23: 14.392
E24: =E23*$C$23 -> 119.185 | F24: =F23*$C$23 -> 34.7 | G24: =G23*$C$23 -> 11.559 | H24: =H23*$C$23 -> 14.411 | I24: =I23*$C$23 -> 10.457 | J24: =J23*$C$23 -> 14.392 | K24: =K23*$C$23 -> 0 | L24: =L23*$C$23 -> 0 | ... AC24: =AC23*$C$23 -> 0
A25: Import of bulls | B25: Million Rupees | C25: 0 | E25: 0 | F25: 0 | G25: 0 | H25: 0 | I25: 0 | J25: 0
E26: =E25*$C$25 -> 0 | F26: =F25*$C$25 -> 0 | G26: =G25*$C$25 -> 0 | H26: =H25*$C$25 -> 0 | I26: =I25*$C$25 -> 0 | J26: =J25*$C$25 -> 0 | K26: =K25*$C$25 -> 0 | L26: =L25*$C$25 -> 0 | ... AC26: =AC25*$C$25 -> 0
A27: Breed Improvement | B27: Million Rupees | C27: 1 | E27: 6.269 | F27: 6.782 | G27: 6.558 | H27: 2.332 | I27: 0 | J27: 0
E28: =E27*$C$27 -> 6.269 | F28: =F27*$C$27 -> 6.782 | G28: =G27*$C$27 -> 6.558 | H28: =H27*$C$27 -> 2.332 | I28: =I27*$C$27 -> 0 | J28: =J27*$C$27 -> 0 | K28: =K27*$C$27 -> 0 | L28: =L27*$C$27 -> 0 | ... AC28: =AC27*$C$27 -> 0
A29: Semen Production | B29: Million Rupees | C29: 1 | E29: =E80 -> 687.5873 | F29: =F80 -> 571.7036 | G29: =G80 -> 112.21981 | H29: =H80 -> 15.015 | I29: =I80 -> 0.378 | J29: =J80 -> 0.1575
E30: =E29*$C$29 -> 687.5873 | F30: =F29*$C$29 -> 571.7036 | G30: =G29*$C$29 -> 112.21981 | H30: =H29*$C$29 -> 15.015 | I30: =I29*$C$29 -> 0.378 | J30: =J29*$C$29 -> 0.1575 | K30: =K29*$C$29 -> 0 | L30: =L29*$C$29 -> 0 | ... AC30: =AC29*$C$29 -> 0
A31: AI Delivery | B31: Million Rupees | C31: 1 | E31: 104.788 | F31: 207.692 | G31: 313.832 | H31: 82.104 | I31: 54.504 | J31: 54.504
E32: =E31*$C$31 -> 104.788 | F32: =F31*$C$31 -> 207.692 | G32: =G31*$C$31 -> 313.832 | H32: =H31*$C$31 -> 82.104 | I32: =I31*$C$31 -> 54.504 | J32: =J31*$C$31 -> 54.504 | K32: =K31*$C$31 -> 0 | L32: =L31*$C$31 -> 0 | ... AC32: =AC31*$C$31 -> 0
A33: LN | B33: Million Rupees | C33: 1 | E33: 64.575 | F33: 62.47 | G33: 0 | H33: 0 | I33: 0 | J33: 0
E34: =E33*$C$33 -> 64.575 | F34: =F33*$C$33 -> 62.47 | G34: =G33*$C$33 -> 0 | H34: =H33*$C$33 -> 0 | I34: =I33*$C$33 -> 0 | J34: =J33*$C$33 -> 0 | K34: =K33*$C$33 -> 0 | L34: =L33*$C$33 -> 0 | ... AC34: =AC33*$C$33 -> 0
A35: Information Systems | B35: Million Rupees | C35: 1 | E35: 133.334 | F35: 22.223 | G35: 0 | H35: 33.334 | I35: 0 | J35: 0
E36: =E35*$C$35 -> 133.334 | F36: =F35*$C$35 -> 22.223 | G36: =G35*$C$35 -> 0 | H36: =H35*$C$35 -> 33.334 | I36: =I35*$C$35 -> 0 | J36: =J35*$C$35 -> 0 | K36: =K35*$C$35 -> 0 | L36: =L35*$C$35 -> 0 | ... AC36: =AC35*$C$35 -> 0
A37: Animal Nutrition - RBP | B37: Million Rupees | C37: 1 | E37: 50.775 | F37: 115.79 | G37: 158.51 | H37: 145.133 | I37: 99.68 | J37: 0 | K37: 0 | L37: 0 | M37: 0 | N37: 0 | O37: 0 | P37: 0 | Q37: 0 | R37: 0 | S37: 0 | T37: 0 | U37: 0 | V37: 0 | W37: 0 | X37: 0 | Y37: 0 | Z37: 0 | AA37: 0 | AB37: 0 | AC37: 0
E38: =E37*$C$37 -> 50.775 | F38: =F37*$C$37 -> 115.79 | G38: =G37*$C$37 -> 158.51 | H38: =H37*$C$37 -> 145.133 | I38: =I37*$C$37 -> 99.68 | J38: =J37*$C$37 -> 0 | K38: =K37*$C$37 -> 0 | L38: =L37*$C$37 -> 0 | ... AC38: =AC37*$C$37 -> 0
A39: Fodder Development | B39: Million Rupees | C39: 1 | E39: 11.112 | F39: 11.112 | G39: 22.224 | H39: 11.112 | I39: 11.112 | J39: 11.112 | K39: 0 | L39: 0 | M39: 0 | N39: 0 | O39: 0 | P39: 0 | Q39: 0 | R39: 0 | S39: 0 | T39: 0 | U39: 0 | V39: 0 | W39: 0 | X39: 0 | Y39: 0 | Z39: 0 | AA39: 0 | AB39: 0 | AC39: 0
E40: =E39*$C$39 -> 11.112 | F40: =F39*$C$39 -> 11.112 | G40: =G39*$C$39 -> 22.224 | H40: =H39*$C$39 -> 11.112 | I40: =I39*$C$39 -> 11.112 | J40: =J39*$C$39 -> 11.112 | K40: =K39*$C$39 -> 0 | L40: =L39*$C$39 -> 0 | ... AC40: =AC39*$C$39 -> 0
A41: Straw Densification Plant | B41: Million Rupees | C41: 1 | E41: 0 | F41: 16.68 | G41: 38.92 | H41: 16.68 | I41: 38.92 | J41: 0 | K41: 0 | L41: 0 | M41: 0 | N41: 0 | O41: 0 | P41: 0 | Q41: 0 | R41: 0 | S41: 0 | T41: 0 | U41: 0 | V41: 0 | W41: 0 | X41: 0 | Y41: 0 | Z41: 0 | AA41: 0 | AB41: 0 | AC41: 0
E42: =$C$41*E41 -> 0 | F42: =$C$41*F41 -> 16.68 | G42: =$C$41*G41 -> 38.92 | H42: =$C$41*H41 -> 16.68 | I42: =$C$41*I41 -> 38.92 | J42: =$C$41*J41 -> 0 | K42: =$C$41*K41 -> 0 | L42: =$C$41*L41 -> 0 | ... AC42: =$C$41*AC41 -> 0
A43: Animal Health care | B43: Million Rupees | C43: 1 | E43: 0 | F43: 0 | G43: 0 | H43: 0 | I43: 0 | J43: 0 | K43: 0 | L43: 0
E44: =E43*$C$43 -> 0 | F44: =F43*$C$43 -> 0 | G44: =G43*$C$43 -> 0 | H44: =H43*$C$43 -> 0 | I44: =I43*$C$43 -> 0 | J44: =J43*$C$43 -> 0 | K44: =K43*$C$43 -> 0 | L44: =L43*$C$43 -> 0 | ... AC44: =AC43*$C$43 -> 0
A45: Milk Collection and Bulking | B45: Million Rupees | C45: 1 | E45: 1484.5491 | F45: 981.49738 | G45: 751.81951 | H45: 786.45491 | I45: 692.62634 | J45: 756.3601 | L45: 0 | N45: 0
E46: =E45*$C$45 -> 1484.5491 | F46: =F45*$C$45 -> 981.49738 | G46: =G45*$C$45 -> 751.81951 | H46: =H45*$C$45 -> 786.45491 | I46: =I45*$C$45 -> 692.62634 | J46: =J45*$C$45 -> 756.3601 | K46: =K45*$C$45 -> 0 | L46: =L45*$C$45 -> 0 | ... AC46: =AC45*$C$45 -> 0
A47: Heifer Rearing | B47: Million Rupees | C47: 1 | E47: 2.8 | F47: 261.464 | G47: 261.464 | H47: 0 | I47: 0 | J47: 0
E48: =E47*$C$47 -> 2.8 | F48: =F47*$C$47 -> 261.464 | G48: =G47*$C$47 -> 261.464 | H48: =H47*$C$47 -> 0 | I48: =I47*$C$47 -> 0 | J48: =J47*$C$47 -> 0 | K48: =K47*$C$47 -> 0 | L48: =L47*$C$47 -> 0 | ... AC48: =AC47*$C$47 -> 0
A49: Total Investment | B49: Million Rupees | E49: =SUM(E24,E26,E28,E30,E32,E34,E36,E38,E40,E42,E44,E46,E48) -> 2664.9744 | F49: =SUM(F24,F26,F28,F30,F32,F34,F36,F38,F40,F42,F44,F46,F48) -> 2292.114 | G49: =SUM(G24,G26,G28,G30,G32,G34,G36,G38,G40,G42,G44,G46,G48) -> 1677.1063 | H49: =SUM(H24,H26,H28,H30,H32,H34,H36,H38,H40,H42,H44,H46,H48) -> 1106.5759 | I49: =SUM(I24,I26,I28,I30,I32,I34,I36,I38,I40,I42,I44,I46,I48) -> 907.67734 | J49: =SUM(J24,J26,J28,J30,J32,J34,J36,J38,J40,J42,J44,J46,J48) -> 836.5256 | K49: =SUM(K24,K26,K28,K30,K32,K34,K36,K38,K40,K42,K44,K46,K48) -> 0 | L49: =L48+L46+L44+L42+L40+L38+L36+L34+L32+L30+L28+L26+L24 -> 0 | M49: =M48+M46+M44+M42+M40+M38+M36+M34+M32+M30+M28+M26+M24 -> 0 | N49: =N48+N46+N44+N42+N40+N38+N36+N34+N32+N30+N28+N26+N24 -> 0 | O49: =O48+O46+O44+O42+O40+O38+O36+O34+O32+O30+O28+O26+O24 -> 0 | P49: =P48+P46+P44+P42+P40+P38+P36+P34+P32+P30+P28+P26+P24 -> 0 | Q49: =Q48+Q46+Q44+Q42+Q40+Q38+Q36+Q34+Q32+Q30+Q28+Q26+Q24 -> 0 | R49: =R48+R46+R44+R42+R40+R38+R36+R34+R32+R30+R28+R26+R24 -> 0 | S49: =S48+S46+S44+S42+S40+S38+S36+S34+S32+S30+S28+S26+S24 -> 0 | ... AC49: =AC48+AC46+AC44+AC42+AC40+AC38+AC36+AC34+AC32+AC30+AC28+AC26+AC24 -> 0
B52: Million Rupees
A54: Animal Health | B54: =1000+110 -> 1110 | C54: 1 | E54: =E55/$D$55*$B$54*$C$54 -> #REF! | F54: =F55/$D$55*$B$54*$C$54 -> #REF! | G54: =G55/$D$55*$B$54*$C$54 -> #REF! | H54: =H55/$D$55*$B$54*$C$54 -> #REF! | I54: =I55/$D$55*$B$54*$C$54 -> #REF! | J54: =J55/$D$55*$B$54*$C$54 -> #REF!
D55: =SUM(E55:J55) -> #REF! | E55: =(E49-E46)+(E17-E16) -> #REF! | F55: =(F49-F46)+(F17-F16) -> #REF! | G55: =(G49-G46)+(G17-G16) -> #REF! | H55: =(H49-H46)+(H17-H16) -> #REF! | I55: =(I49-I46)+(I17-I16) -> #REF! | J55: =(J49-J46)+(J17-J16) -> #REF!
A57: Project Management Costs | B57: 2000 | C57: 1
A58: Milk Collection and Bulking | B58: Million Rupees | E58: =E61/$D$61*$C$61*$C$57 -> #REF! | F58: =F61/$D$61*$C$61*$C$57 -> #REF! | G58: =G61/$D$61*$C$61*$C$57 -> #REF! | H58: =H61/$D$61*$C$61*$C$57 -> #REF! | I58: =I61/$D$61*$C$61*$C$57 -> #REF! | J58: =J61/$D$61*$C$61*$C$57 -> #REF!
A59: Productivity Enhancement Activities | B59: Million Rupees | E59: =E62/$D$61*$C$61*$C$57 -> #REF! | F59: =F62/$D$61*$C$61*$C$57 -> #REF! | G59: =G62/$D$61*$C$61*$C$57 -> #REF! | H59: =H62/$D$61*$C$61*$C$57 -> #REF! | I59: =I62/$D$61*$C$61*$C$57 -> #REF! | J59: =J62/$D$61*$C$61*$C$57 -> #REF!
A60: Total | E60: =SUM(E58:E59) -> #REF! | F60: =SUM(F58:F59) -> #REF! | G60: =SUM(G58:G59) -> #REF! | H60: =SUM(H58:H59) -> #REF! | I60: =SUM(I58:I59) -> #REF! | J60: =SUM(J58:J59) -> #REF!
A61: Milk Collection and Bulking | C61: =D61/C63*B57 -> #REF! | D61: =SUM(E61:J61) -> 5453.3073 | E61: =E45 -> 1484.5491 | F61: =F45 -> 981.49738 | G61: =G45 -> 751.81951 | H61: =H45 -> 786.45491 | I61: =I45 -> 692.62634 | J61: =J45 -> 756.3601
A62: Productivity Enhancement Activities | C62: =D62/C63*B57 -> #REF! | D62: =SUM(E62:J62) -> #REF! | E62: =E49-E45+E54 -> #REF! | F62: =F49-F45+F54 -> #REF! | G62: =G49-G45+G54 -> #REF! | H62: =H49-H45+H54 -> #REF! | I62: =I49-I45+I54 -> #REF! | J62: =J49-J45+J54 -> #REF!
A63: Total | C63: =SUM(D61:D62) -> #REF!
A65: Total Capex
A66: Productivity Enhancement Activities | E66: =SUM(E24,E26,E28,E30,E32,E34,E36,E38,E40,E42,E44,E48)+E54 -> #REF! | F66: =SUM(F24,F26,F28,F30,F32,F34,F36,F38,F40,F42,F44,F48)+F54 -> #REF! | G66: =SUM(G24,G26,G28,G30,G32,G34,G36,G38,G40,G42,G44,G48)+G54 -> #REF! | H66: =SUM(H24,H26,H28,H30,H32,H34,H36,H38,H40,H42,H44,H48)+H54 -> #REF! | I66: =SUM(I24,I26,I28,I30,I32,I34,I36,I38,I40,I42,I44,I48)+I54 -> #REF! | J66: =SUM(J24,J26,J28,J30,J32,J34,J36,J38,J40,J42,J44,J48)+J54 -> #REF!
A67: Milk Collection and Bulking | E67: =E46 -> 1484.5491 | F67: =F46 -> 981.49738 | G67: =G46 -> 751.81951 | H67: =H46 -> 786.45491 | I67: =I46 -> 692.62634 | J67: =J46 -> 756.3601
A71: Semen Stations
A72: Semen produced in NDSP semen stations and from NDSP bulls | B72: lakh Doses | E72: 59.284 | F72: 142.92966 | G72: 210.27037 | H72: 308.63953 | I72: 341.20312 | J72: 363.98827 | K72: 381.28827 | L72: 395.06827 | M72: 411.55827 | N72: 420.48827 | O72: 420.48827 | P72: 420.48827 | Q72: 420.48827 | R72: 420.48827 | S72: 420.48827 | T72: 420.48827 | U72: 420.48827 | V72: 420.48827 | W72: 420.48827 | X72: 420.48827 | Y72: 420.48827 | Z72: 420.48827 | AA72: 420.48827 | AB72: 420.48827 | AC72: 420.48827
A73: Total Semen Production from New SS under NDP | B73: lakh Doses | E73: 0 | F73: 0 | G73: 10 | H73: 21.5 | I73: 35 | J73: 41.5 | K73: 58.8 | L73: 72.58 | M73: 89.07 | N73: 98 | O73: 98 | P73: 98 | Q73: 98 | R73: 98 | S73: 98 | T73: 98 | U73: 98 | V73: 98 | W73: 98 | X73: 98 | Y73: 98 | Z73: 98 | AA73: 98 | AB73: 98 | AC73: 98
A74: Total Semen Production from Strengthened SS under NDP-I | B74: lakh Doses | E74: =E72-E73 -> 59.284 | F74: =F72-F73 -> 142.92966 | G74: =G72-G73 -> 200.27037 | H74: =H72-H73 -> 287.13953 | I74: =I72-I73 -> 306.20312 | J74: =J72-J73 -> 322.48827 | K74: =K72-K73 -> 322.48827 | L74: =L72-L73 -> 322.48827 | ... AC74: =AC72-AC73 -> 322.48827
A75: Semen produced by non-NDSP semen stations but from NDSP bulls | B75: lakh Doses | E75: 0 | F75: 0 | G75: 0 | H75: 0 | I75: 23.436168 | J75: 111.76965 | K75: 94.469654 | L75: 80.689654 | M75: 64.199654 | N75: 55.269654 | O75: 55.269654 | P75: 55.269654 | Q75: 55.269654 | R75: 55.269654 | S75: 55.269654 | T75: 55.269654 | U75: 55.269654 | V75: 55.269654 | W75: 55.269654 | X75: 55.269654 | Y75: 55.269654 | Z75: 55.269654 | AA75: 55.269654 | AB75: 55.269654 | AC75: 55.269654
A77: Capital Expenses for New SS | B77: Million Rs. | E77: 388.3333 | F77: 38.73975 | G77: 14.7945 | H77: 0.2205 | I77: 0.1575 | J77: 0
A78: Capital Expenses for second New SS | B78: Million Rs. | E78: 0 | F78: =E77 -> 388.3333 | G78: =F77 -> 38.73975 | H78: =G77 -> 14.7945 | I78: =H77 -> 0.2205 | J78: =I77 -> 0.1575 | K78: =J77 -> 0
A79: Capital Expenses for Strengthening SS | B79: Million Rs. | E79: 299.254 | F79: 144.63056 | G79: 58.685556 | H79: 0 | I79: 0 | J79: 0
A80: Total Capital Expenses | B80: Million Rs. | E80: =SUM(E77:E79) -> 687.5873 | F80: =SUM(F77:F79) -> 571.7036 | G80: =SUM(G77:G79) -> 112.21981 | H80: =SUM(H77:H79) -> 15.015 | I80: =SUM(I77:I79) -> 0.378 | J80: =SUM(J77:J79) -> 0.1575 | K80: =SUM(K77:K79) -> 0 | L80: =SUM(L77:L79) -> 0
A82: Operating Expenses from New SS Model | B82: Million Rs. | E82: 55.197528 | F82: 58.640039 | G82: 66.876776 | H82: 68.742903 | I82: 71.8036 | J82: 76.816935 | K82: 80.5218 | L82: 82.283306 | M82: 85.211249 | N82: 88.861237 | O82: 89.635259 | P82: 87.395996 | Q82: 85.276625 | R82: 83.786486 | S82: 82.748988 | T82: 81.847321 | U82: =T82 -> 81.847321 | V82: =U82 -> 81.847321 | W82: =V82 -> 81.847321 | X82: =W82 -> 81.847321 | Y82: =X82 -> 81.847321 | Z82: =Y82 -> 81.847321 | AA82: =Z82 -> 81.847321 | AB82: =AA82 -> 81.847321 | AC82: =AB82 -> 81.847321
A83: Operating expenses for Second New SS | B83: Million Rs. | E83: =0 -> 0 | F83: =E82 -> 55.197528 | G83: =F82 -> 58.640039 | H83: =G82 -> 66.876776 | I83: =H82 -> 68.742903 | J83: =I82 -> 71.8036 | K83: =J82 -> 76.816935 | L83: =K82 -> 80.5218 | M83: =L82 -> 82.283306 | ... AC83: =AB82 -> 81.847321
A84: Training Expenses for New SS | B84: Million Rs. | E84: 0 | F84: 1.2724 | G84: 0.09696 | H84: 0.17044 | I84: 0.10312 | J84: 0.02912
A85: Training Expenses for Second New SS | B85: Million Rs. | E85: 0 | F85: =E84 -> 0 | G85: =F84 -> 1.2724 | H85: =G84 -> 0.09696 | I85: =H84 -> 0.17044 | J85: =I84 -> 0.10312 | K85: =J84 -> 0.02912
A89: RBP
A90: Operating Expenses for NGCs | E90: 81.751109 | F90: 214.67603 | G90: 298.32417 | H90: 312.4797 | I90: 230.27004 | J90: 185.37419
A91: Operating Expenses for DCSs | E91: 72.89 | F91: 202.987 | G91: 344.515 | H91: 378.0526 | I91: 345.41592 | J91: 83.511664
A92: Total Operating Expenses for NGCs and DCSs | E92: =SUM(E90:E91) -> 154.64111 | F92: =SUM(F90:F91) -> 417.66303 | G92: =SUM(G90:G91) -> 642.83917 | H92: =SUM(H90:H91) -> 690.5323 | I92: =SUM(I90:I91) -> 575.68596 | J92: =SUM(J90:J91) -> 268.88586 | K92: =J92 -> 268.88586 | L92: =K92 -> 268.88586 | M92: =L92 -> 268.88586 | N92: =M92 -> 268.88586 | O92: =N92 -> 268.88586 | P92: =O92 -> 268.88586 | Q92: =P92 -> 268.88586 | R92: =Q92 -> 268.88586 | ... AC92: =AB92 -> 268.88586
A94: Fodder Development
A95: Operating Exp for Fodder Seed Processing Plants | E95: =SUM(E96:E101) -> 8.0055 | F95: =SUM(F96:F101) -> 23.9055 | G95: =SUM(G96:G101) -> 55.7055 | H95: =SUM(H96:H101) -> 63.711 | I95: =SUM(I96:I101) -> 79.611 | J95: =SUM(J96:J101) -> 87.6165 | K95: =SUM(K96:K101) -> 87.6165 | L95: =K95 -> 87.6165 | M95: =L95 -> 87.6165 | N95: =M95 -> 87.6165 | O95: =N95 -> 87.6165 | P95: =O95 -> 87.6165 | Q95: =P95 -> 87.6165 | R95: =Q95 -> 87.6165 | S95: =R95 -> 87.6165 | ... AC95: =AB95 -> 87.6165
A96: Year 1 : South region | B96: 26685 | E96: =$B$96*1*300/1000000 -> 8.0055 | F96: =$B$96*1*300/1000000 -> 8.0055 | G96: =$B$96*1*300/1000000 -> 8.0055 | H96: =$B$96*1*300/1000000 -> 8.0055 | I96: =$B$96*1*300/1000000 -> 8.0055 | J96: =$B$96*1*300/1000000 -> 8.0055 | K96: =$B$96*1*300/1000000 -> 8.0055
A97: Year 2 : North region | B97: 53000 | F97: =$B$97*1*300/1000000 -> 15.9 | G97: =$B$97*1*300/1000000 -> 15.9 | H97: =$B$97*1*300/1000000 -> 15.9 | I97: =$B$97*1*300/1000000 -> 15.9 | J97: =$B$97*1*300/1000000 -> 15.9 | K97: =$B$97*1*300/1000000 -> 15.9
A98: Year 3 : North Region 2 plants | G98: =G97*2 -> 31.8 | H98: =H97*2 -> 31.8 | I98: =I97*2 -> 31.8 | J98: =J97*2 -> 31.8 | K98: =K97*2 -> 31.8
A99: Year 4 : South Region : 1 plant | H99: =E96 -> 8.0055 | I99: =F96 -> 8.0055 | J99: =G96 -> 8.0055 | K99: =H96 -> 8.0055
A100: Year 5 : North Region : 1 plant | I100: =F97 -> 15.9 | J100: =G97 -> 15.9 | K100: =H97 -> 15.9
A101: Year 6: South Region : 1 plant | J101: =E96 -> 8.0055 | K101: =F96 -> 8.0055
A102: Operating Exp for Straw Densification Plants | C102: 7020 | E102: =$C$102*'Feed and Fodder (F) Zone.2'!E24/1000000 -> 0 | F102: =$C$102*'Feed and Fodder (F) Zone.2'!F24/1000000 -> 84.24 | G102: =$C$102*'Feed and Fodder (F) Zone.2'!G24/1000000 -> 84.24 | H102: =$C$102*'Feed and Fodder (F) Zone.2'!H24/1000000 -> 168.48 | I102: =$C$102*'Feed and Fodder (F) Zone.2'!I24/1000000 -> 168.48 | J102: =$C$102*'Feed and Fodder (F) Zone.2'!J24/1000000 -> 168.48 | K102: =$C$102*'Feed and Fodder (F) Zone.2'!K24/1000000 -> 168.48 | L102: =$C$102*'Feed and Fodder (F) Zone.2'!L24/1000000 -> 168.48 | ... AC102: =$C$102*'Feed and Fodder (F) Zone.2'!AC24/1000000 -> 168.48
A103: Total | E103: =SUM(E95,E102) -> 8.0055 | F103: =SUM(F95,F102) -> 108.1455 | G103: =SUM(G95,G102) -> 139.9455 | H103: =SUM(H95,H102) -> 232.191 | I103: =SUM(I95,I102) -> 248.091 | J103: =SUM(J95,J102) -> 256.0965 | K103: =SUM(K95,K102) -> 256.0965 | L103: =SUM(L95:L102) -> 256.0965 | M103: =SUM(M95:M102) -> 256.0965 | N103: =SUM(N95:N102) -> 256.0965 | O103: =SUM(O95:O102) -> 256.0965 | P103: =SUM(P95:P102) -> 256.0965 | Q103: =SUM(Q95:Q102) -> 256.0965 | R103: =SUM(R95:R102) -> 256.0965 | S103: =SUM(S95:S102) -> 256.0965 | ... AC103: =SUM(AC95:AC102) -> 256.0965
A107: Milk collection and Bulking
A108: Total Operating Expenses | E108: =SUM(E109:E111) -> #REF! | F108: =SUM(F109:F111) -> #REF! | G108: =SUM(G109:G111) -> #REF! | H108: =SUM(H109:H111) -> #REF! | I108: =SUM(I109:I111) -> #REF! | J108: =SUM(J109:J111) -> #REF! | K108: =SUM(K109:K111) -> #REF! | L108: =SUM(L109:L111) -> #REF! | ... AC108: =SUM(AC109:AC111) -> #REF!
A109: Operating Expenses | B109: Million Rs. | E109: 665.10405 | F109: 484.61395 | G109: 414.79865 | H109: 398.00395 | I109: 371.5205 | J109: 383.8063 | K109: =J109 -> 383.8063 | L109: =K109 -> 383.8063 | M109: =L109 -> 383.8063 | N109: =M109 -> 383.8063 | O109: =N109 -> 383.8063 | P109: =O109 -> 383.8063 | Q109: =P109 -> 383.8063 | R109: =Q109 -> 383.8063 | ... AC109: =AB109 -> 383.8063
A110: BMCU: Operating expenditure | B110: Million Rs. | C110: =#REF! -> #REF! | E110: =$C$110*(#REF!*1.028)*365 -> #REF! | F110: =$C$110*(#REF!*1.028)*365 -> #REF! | G110: =$C$110*(#REF!*1.028)*365 -> #REF! | H110: =$C$110*(#REF!*1.028)*365 -> #REF! | I110: =$C$110*(#REF!*1.028)*365 -> #REF! | J110: =$C$110*(#REF!*1.028)*365 -> #REF! | K110: =$C$110*(#REF!*1.028)*365 -> #REF! | L110: =$C$110*(#REF!*1.028)*365 -> #REF! | ... AC110: =$C$110*(#REF!*1.028)*365 -> #REF!
A111: Village level institutions operating expenditure | B111: Million Rs. | C111: 0.98 | E111: =(#REF!-#REF!)*1000*$C$111 -> #REF! | F111: =(#REF!-#REF!)*1000*$C$111 -> #REF! | G111: =(#REF!-#REF!)*1000*$C$111 -> #REF! | H111: =(#REF!-#REF!)*1000*$C$111 -> #REF! | I111: =(#REF!-#REF!)*1000*$C$111 -> #REF! | J111: =(#REF!-#REF!)*1000*$C$111 -> #REF! | K111: =(#REF!-#REF!)*1000*$C$111 -> #REF! | L111: =(#REF!-#REF!)*1000*$C$111 -> #REF! | ... AC111: =(#REF!-#REF!)*1000*$C$111 -> #REF!
A113: BMC CAPACITY
A114: Parameters | D114: Phase I : Year ended 31 March
C115: 0.8 | D115: 2011 | E115: 2012 | F115: 2013 | G115: 2014 | H115: 2015 | I115: 2016 | J115: 2017 | K115: 2018 | L115: 2019 | M115: 2020 | N115: 2021 | O115: 2022 | P115: 2023 | Q115: 2024 | R115: 2025 | S115: 2026 | T115: 2027 | U115: 2028 | V115: 2029 | W115: 2030 | X115: 2031 | Y115: 2032 | Z115: 2033 | AA115: 2034 | AB115: 2035 | AC115: 2036
A117: Build up of BMC capacity | B117: Million LPD | C117: Cumulative | D117: 0.47 | E117: 0.753 | F117: 1.028 | G117: 1.276 | H117: 1.47 | I117: 1.656 | J117: 1.656 | K117: 1.656 | L117: 1.656 | M117: 1.656 | N117: 1.656 | O117: 1.656 | P117: 1.656 | Q117: 1.656 | R117: 1.656 | S117: 1.656 | T117: 1.656 | U117: 1.656 | V117: 1.656 | W117: 1.656 | X117: 1.656 | Y117: 1.656 | Z117: 1.656 | AA117: 1.656 | AB117: 1.656 | AC117: 1.656
A118: Build up of BMC capacity | B118: Million LPD | C118: Incremental | D118: 0.47 | E118: 0.283 | F118: 0.275 | G118: 0.248 | H118: 0.194 | I118: 0.186
A119: Total Build up of BMC Capacity | B119: Million LPD | C119: Cumulative | D119: 0.376 | E119: 0.6024 | F119: 0.8224 | G119: 1.0208 | H119: 1.176 | I119: 1.3248 | J119: 1.3248 | K119: 1.3248 | L119: 1.3248 | M119: 1.3248 | N119: 1.3248 | O119: 1.3248 | P119: 1.3248 | Q119: 1.3248 | R119: 1.3248 | S119: 1.3248 | T119: 1.3248 | U119: 1.3248 | V119: 1.3248 | W119: 1.3248 | X119: 1.3248 | Y119: 1.3248 | Z119: 1.3248 | AA119: 1.3248 | AB119: 1.3248 | AC119: 1.3248
A121: Total Build up of BMC Capacity | B121: Million Kg PD | C121: Cumulative | D121: =+D119*1.03 -> 0.38728 | E121: =+E119*1.03 -> 0.620472 | F121: =+F119*1.03 -> 0.847072 | G121: =+G119*1.03 -> 1.051424 | H121: =+H119*1.03 -> 1.21128 | I121: =+I119*1.03 -> 1.364544 | J121: =+J119*1.03 -> 1.364544 | K121: =+K119*1.03 -> 1.364544 | ... AC121: =+AC119*1.03 -> 1.364544
D122: =+D121*365/1000 -> 0.1413572 | E122: =+E121*365/1000 -> 0.22647228 | F122: =+F121*365/1000 -> 0.30918128 | G122: =+G121*365/1000 -> 0.38376976 | H122: =+H121*365/1000 -> 0.4421172 | I122: =+I121*365/1000 -> 0.49805856 | J122: =+J121*365/1000 -> 0.49805856
A123: Cost Savings due to BMC Handling | B123: Rs/l | C123: =+'Comp B-BMC'!J23 -> 0.95084341
B124: Rs/Kg | C124: =+C123/1.03 -> 0.92314894
...

Sheet Comp B-BMC
A1: Details of savings in cost to Union/Dairy plant due to use of BMC's vis a vis Cans for milk collection | G1: Benefits to DCS by installing BMCU
A2: Sr No. | B2: Details / particulas of savings | C2: Range of saving in cost in Rs per lt of milk * | E2: Saving | G2: Sr No. | H2: Details / particulas of savings | I2: Range of saving in cost in Rs per lt of milk * | K2: Saving
C3: Min | D3: Max | I3: Min | J3: Max
A4: 1 | B4: Transportation Cost ^^ : There is saving in cost of raw milk transporation to dairy in case BMC's are installed. The cost of transportation varies based on number of factors such as density of milk procurement , route length etc . The details are worked based on data conveyed by the different dairy plants . | C4: 0.15 | D4: 0.205 | E4: 0.15 | G4: 1 | H4: Elimination of variation in quantity,fat and SNF. As informed , the average savings comes to approx 0.105% ^^of FAT and 0.09 % ^^of SNF. Considering rate of milk as Rs 18.00 to 20.00 per Kg , the saving is | I4: 0.32 | J4: 0.36 | K4: =I4 -> 0.32
A5: 2 | B5: Due to elimination of need for refrigeration / can cleaning/ sterilization with steam . The saving due to elimination of chilling comes to approx Rs 0.10-0.17 per liltre of milk and due to elimination of steam/ can operation in can washer comes to approx Rs 0.02 to 0.03 paise per litre of milk. | C5: 0.15 | D5: 0.18 | E5: =C5 -> 0.15 | G5: 2 | H5: Elimination of sourage / curdling of milk supplied to dairy plant. Considering sourage/ curdling of approx 1.5 % ^^of milk ( as reported by study conducted by Center for Management Development, Trivandrum) and rate of Rs 18.00 to Rs 20.00 per Kg of milk, the saving is | I5: =1.5*14/100 -> 0.21 | J5: =18*1.5/100 -> 0.27 | K5: =I5 -> 0.21
A6: 3 | B6: Due to reduction in labour charges for handling cans and tankers at dairy plant. Considering minimum volume of 10,000 lpd, the can reception ( for 2 shifts) shall need 6 handling persons @ Rs 100 per person ( Rs 0.06 per lt ). In case of handlin tankers , only 2 handling persons ae needed. So the saving is approx rs 0.04 per litre of milk handled. | C6: 0.04 | D6: 0.04 | E6: =C6 -> 0.04 | G6: 3 | H6: Due to reduction in manpower for handling cans . Saving of 1 person per DCS @Rs 100 per day per peson for handling approx 2000 lts to 2400 lts of milk per day | I6: =100/2400 -> 0.041666667 | J6: =100/2000 -> 0.05 | K6: =I6 -> 0.041666667
A7: 4 | B7: Elimination of cost related to replacement/ damage to the cans. The life of cans is taken as 7 years and cost of repairs is approx Rs 2500 in 7 years. | C7: 0.02 | D7: 0.03 | E7: 0 | G7: 4 | H7: Due to receipt of Quality Incentive from Union for good quality of milk . Generally it is (minimum)@ Rs3 to 5 per Kg fat for average 5-6% fat | I7: =(5/100)*3 -> 0.15 | J7: =(6/100)*5 -> 0.3 | K7: 0
A8: 5 | B8: Due to need for keeping lower pasteurisation temp in case of receipt of milk through BMC's and cans . Difference of approx 2 to 3 deg C | C8: 0.05 | D8: 0.06 | E8: =C8 -> 0.05 | H8: Total | I8: =SUM(I4:I7) -> 0.72166667 | J8: =SUM(J4:J7) -> 0.98 | K8: =SUM(K4:K7) -> 0.57166667
B9: TOTAL | C9: =SUM(C4:C8) -> 0.41 | D9: =SUM(D4:D8) -> 0.515 | E9: =SUM(E4:E8) -> 0.39 | H9: Note: In addition to the above , the DCS gets paid from Union for cooling and BMC cleaning charges approx @ Rs 0.18 to Rs 0.20 per lt of milk. | K9: 0.2
B10: Note : *The range is taken on lower scale. | G10: The Union would pay Re .20/ltire to the DCS for the milk handled as savings from the non-operation of chilling centre
B11: ^^ Report on evaluation (2003-04 to 2007-08) prepared by Centre for Management Development, Trivandrum to study the scheme "Stregthening Infrastructure for Quality and Clean Milk Production" implemented by Dept of AHDF, Govt of India
B12: Other benefits : - | R12: Economic Benefit Calculation | T12: Economic
B13: 1. Increase in handling capacity of plant as no restriction on milk receipt time ( morning and evening). | H13: Net Cost savings | T13: Cost | U13: Factor
B14: 2. In case of supply of bulk mik to other nearby unions ( up to 250 kms), in case BMC's are installed then the milk can be transported directly to other union without bringing to dairy for pasteurisation / chilling ( thus saving in cost). | Q14: 0.6 | R14: Transport Fuel Cost | T14: 0.063 | U14: 0.7
B15: 3. Due to good quality of milk without dust / extraneous matter, performance of pasteurisers and separators is better and maintenance cost goes down | F15: Transportation | J15: 0.15 | K15: 0.19693654 | Q15: 0.6 | R15: Power savings due to elimination of chilling and steam sterilization | T15: 0.36 | U15: 4
B16: 4. Marked improvement in quality of market liquid milk and products such as powder, paneer, dahi etc. | F16: Opearations | J16: 0.32 | K16: 0.42013129 | Q16: 1 | R16: Cost savings due to elimination of cans | T16: 0
B17: 5. Adulteration of milk and spillage from cans during transport can be eliminated | F17: Handling | J17: 0.081666667 | K17: 0.10722101 | Q17: 1 | R17: Power savings due to lower pasteurization temp (by 2-3 degrees) needs | T17: 0.2 | U17: 4
B18: 6.This offers a risk free working enivronment in dairies and innumerable options for value addition | F18: Processing | J18: 0.21 | K18: 0.27571116 | Q18: 0.5 | R18: Reduced variation in SNF and Fat | T18: 0.16170876 | U18: 1.0106797
B19: 7. Saving of initial investment on purchase of cans | Q19: 1 | R19: Elimination of sourage and curdling of milk | T19: 0.21224274 | U19: 1.0106797
H20: 2007/08 prices | J20: =SUM(J15:J19) -> 0.76166667 | T20: =+SUM(T14:T19) -> 0.9969515
Q21: Ratio of Economic to Financial Price
I22: 1.2483721
H23: 2010/11 prices | J23: =+J20*$I$22 -> 0.95084341 | Q23: =+Q25 -> 1.3089079 | T23: =+T20*I22 -> 1.2445664
Q25: =+T23/J23 -> 1.3089079

Sheet Feed and Fodder
A1: Sr. No. | B1: Study | C1: Authors | D1: Source | E1: Year of Publication | F1: Area of Study | G1: Sample size | H1: Breed of Buffalos and Cows | I1: Current Yield | J1: No. of farmers considered | K1: Type of farmers | L1: IMPACT Indicators | M1: Without | N1: With | Q1: Increase/Decrease | T1: Benefits Addressed | U1: Remarks
A3: 1 | B3: Assesment of Economic Impact of Implementing RBP in Lactating Cows and Buffaloes under field conditions | C3: MR Garg, S A Biradar and A Kannan | D3: Indian Journal of Animal Nutrition | E3: 2009 | F3: Junagadh in Gujarat | G3: Lactating Animals : 2536 Buffloes : 1709 Cows :827 | H3: Buffaloes : Jaffrabadi Cows : Gir | I3: 6-12 kg/day | J3: 1250 | K3: Marginal (<1 hectare) | L3: Average Milk Yield/Day | M3: 8.25 | N3: 8.83 | Q3: =N3-M3 -> 0.58 | S3: 0.5 | T3: 1. Increase in milk productivity 2. Improved milk quality (milk solids) 3.Minimized unit cost of production 4. Opportunity cost of saved fodder can be calculated | U3: Lactation trial of 120 days duration was conducted on 2536 lactating animals in 25 villages in Junagadh District in Guajrat
L4: Average fat content(%) | M4: 5.79 | N4: 6.29 | Q4: =N4-M4 -> 0.5 | S4: 0.0025
L5: Daily Feeding Cost/kg Milk Production | M5: =9.45 -> 9.45 | N5: 7.47 | Q5: =M5-N5 -> 1.98 | R5: =Q5/M5 -> 0.20952381
S6: =R5*0.9 -> 0.18857143 | U6: 90 % of the total percentage of reduction of daily feeding costs considered ( cosnervatism)
A7: 2 | B7: Effect of RBP on Methane Emission Reductions in Lactating Animals Under Field Conditions | C7: A Kannan and M R Garg | D7: Indian Journal of Dairy Sciences | E7: 2009 | F7: Junagadh district in Gujarat | G7: Buffloes : 22 Cows :5 | H7: Buffaloes : Jaffrabadi Cows : Gir | I7: Buffalo : 3rd-5th lactation. Prodn; 8-12 kg milk;6-7.5%fat , Cows : 4th -6th Lactation, Prodn: 9.5-12.5 kg, 4-4.5%fat | J7: 10 | K7: -- | L7: Energy Loss as methane (% of gross energy) - Buffalo | M7: 5.64 | N7: 4.9 | Q7: =5.64-4.9 -> 0.74 | T7: Reduction in methane emissions due to RBP | U7: Baseline emissions of alll the animals were estimated using Sulphur Hexaflouride techinque and then ration was balanced as per their nutrient requirement.
L8: Energy Loss as methane (% of gross energy)- Cows | M8: 5.85 | N8: 5.14 | Q8: =5.85-5.14 -> 0.71
L9: Methane Emission in buffaloes (g/animal/day) | M9: 232.48 | N9: 199.6 | Q9: =M9-N9 -> 32.88 | R9: =Q9/M9*100 -> 14.143152 | U9: Total Reduction in Methane emissions in buffaloes and cows are 14.14% and 13.29% respectively but for our calculations we are taking conservative estimates of 10% reduction
M10: 237.74 | N10: 206.13 | Q10: =M10-N10 -> 31.61 | R10: =Q10/M10*100 -> 13.296038
A11: 3 | B11: Effect of Ration Balancing on Methane Emission and Milk Production in Lactating Animals under Field Conditions in Raebareli District of Uttar Pradesh | C11: A Kannan, M.R. Garg and Pankaj Singh | D11: Indian Journal of Animal Nutrition | E11: 2010 | F11: Raebareli District of Uttar Pradesh | G11: Buffaloes : 13 Cows : 13 | I11: Buffalo : 2nd-4th lactation. Prodn; 4-6.5 kg milk; 5.0-6.5%fat , Cows : 3rd -4th Lactation, Prodn: 4.0-6.5 kg, 3.5-5.0%fat | J11: 20 | K11: -- | L11: Energy Loss as methane (% of gross energy) - Buffalo | M11: 6.48 | N11: 5.78 | Q11: =5.64-4.9 -> 0.74 | T11: Reduction in methane emissions due to RBP | U11: Total reduction in Methane emission in buffaloes and cows is 10.48 and 11.37%, respectively. For our calculations we have taken a conservative estimate of 10% methane emission reduction due to RBP.
L12: Energy Loss as methane (% of gross energy)- Cows | M12: 6.46 | N12: 5.55
L13: Milk yield (Kg/day) : Buffaloes | M13: 5.25 | N13: 5.93 | Q13: =N13-M13 -> 0.68
L14: Milk yield (Kg/day) : Cows | M14: 4.95 | N14: 5.5 | Q14: =N14-M14 -> 0.55 | S14: =0.5 -> 0.5
L15: Milk fat (%) : Buffaloes | M15: 5.98 | N15: 6.32 | Q15: =N15-M15 -> 0.34 | S15: =AVERAGE(Q15,Q16) -> 0.265
L16: Milf fat (%) : Cows | M16: 4.2 | N16: 4.39 | Q16: =N16-M16 -> 0.19
L17: Methane Emission in buffaloes (g/animal/day) | M17: 214.68 | N17: 192.19 | R17: 0.1048
L18: Methane Emission in cows (g/animal/day) | M18: 195.79 | N18: 173.54 | R18: 0.1137
M19: =+AVERAGE(M9,M17) -> 223.58
B22: Type | C22: Proportion of Animals | D22: Methane Emissions Kg/animal/annum | G22: References
B23: Indigenous | C23: 0.2 | D23: 28 | G23: NATCOM, 2004: India's Initial National Communication to UNFCCC, Ministry of Enviornment & Forests, Government of India.
B24: Cross Bred | C24: 0.5 | D24: =195.79*365/1000 -> 71.46335 | E24: (@195.79g/animal/day) | G24: Kannan,A., Garg,MR and Pankaj Singh.2010. Effect of Ration Balancing on Methane Emission and Milk Production in Lactating Animals under Field Conditions in Rae Bareli district of Uttar Pradesh . Indian journal of Animal Nutrition.27(2):103-108
B25: Bufflaoes | C25: 0.3 | D25: =223.58*365/1000 -> 81.6067 | E25: (@223.58 g/animal/day) | G25: Kannan,A. and Garg M R 2009. Effect of RBP on Methane Emission Reductions in Lactating Animals Under Field Conditions. Indian Journal of Dairy Science 62(4)292-296. Kannan,A., Garg,MR and Pankaj Singh.2010. Effect of Ration Balancing on Methane Emission and Milk Production in Lactating Animals under Field Conditions in Rae Bareli district of Uttar Pradesh . Indian journal of Animal Nutrition.27(2):103-108
B27: Average/Animal Per annum (Methane emission) | C27: kg/animal/year | D27: =(D23*C23)+(D24*C24)+(D25*C25) -> 65.813685 | E27: =+D27*C32 -> 1645.3421
B30: Reduction of methane emissions by 10% | C30: 0.1 | D30: =D27*C30 -> 6.5813685 | E30: Garg et al. (2009); Kannan and Garg (2009); Kannan et al. (2010)
B32: Carbon di-oxide equivalent ( 1 Kg of Methane = 25 Kg of CO2) | C32: 25 | D32: =D30*C32 -> 164.53421 | E32: Website of IPCC, 2007. Climate Change 2007. The Physical Science Basis. Intergovernmental Panel on Climate Change.
B33: Certified Emission Reductions (CER) | C33: Tonnes/Animal/Annum | D33: =D32/1000 -> 0.16453421
B34: Benefit per animal per annum @ Rs. 740 per CER (Rs.) | C34: 740 | D34: =D33*C34 -> 121.75532 | E34: Spot carbon credit price taken from National Commodity & Derivatives Exchange Limited of India, 2010
D38: =+D33*'Feed and Fodder (F) Zone.1'!S6/1000000 -> 0.44740143
H40: =F40*G40 -> 0
H41: =F41*G41 -> 0

Sheet Feed and Fodder (F) Zone.1
A1: Contribution of Feed & Nutrition to Additional Milk Production
C2: Current | E2: 2011-12 | F2: 2012-13 | G2: 2013-14 | H2: 2014-15 | I2: 2015-16 | J2: 2016-17 | K2: 2017-18 | L2: 2018-19 | M2: 2019-20 | N2: 2020-21 | O2: 2021-22 | P2: 2022-23 | Q2: 2023-24 | R2: 2024-25 | S2: 2025-26 | T2: 2026-27 | U2: 2027-28 | V2: 2028-29 | W2: 2029-30 | X2: 2030-31 | Y2: 2031-32 | Z2: 2032-33 | AA2: 2033-34 | AB2: 2034-35 | AC2: 2036-37
A3: A. | B3: Ration Balancing Programme RBP
B4: PDAs (Nos.) | C4: 25 | E4: 830 | F4: 1270 | G4: 730 | H4: 730 | I4: 1630 | J4: 2010 | K4: =J4 -> 2010 | L4: =K4 -> 2010 | M4: =L4 -> 2010 | N4: =M4 -> 2010 | O4: =N4 -> 2010 | P4: =O4 -> 2010 | Q4: =P4 -> 2010 | R4: =Q4 -> 2010 | S4: =R4 -> 2010
B5: Villages (Nos) | E5: 5500 | F5: 11100 | G5: 17700 | H5: 27300 | I5: 35880 | J5: 40320 | K5: 40320 | L5: 40320 | M5: 40320 | N5: 40320 | O5: 40320 | P5: 40320 | Q5: 40320 | R5: 40320 | S5: 40320 | T5: 40320 | U5: 40320 | V5: 40320 | W5: 40320 | X5: 40320 | Y5: 40320 | Z5: 40320 | AA5: 40320 | AB5: 40320 | AC5: 40320
B6: Animals covered (Nos) | E6: 366000 | F6: 741000 | G6: 1188000 | H6: 1818000 | I6: 2392800 | J6: 2719200 | K6: 2719200 | L6: 2719200 | M6: 2719200 | N6: 2719200 | O6: 2719200 | P6: 2719200 | Q6: 2719200 | R6: 2719200 | S6: 2719200 | T6: 2719200 | U6: 2719200 | V6: 2719200 | W6: 2719200 | X6: 2719200 | Y6: 2719200 | Z6: 2719200 | AA6: 2719200 | AB6: 2719200 | AC6: 2719200
B7: Average increase in milk production due to the programme (KgPD/Animal) | E7: ='Feed and Fodder'!S14 -> 0.5 | F7: =E7 -> 0.5 | G7: =F7 -> 0.5 | H7: =G7 -> 0.5 | I7: =H7 -> 0.5 | J7: =I7 -> 0.5 | K7: =J7 -> 0.5 | L7: =K7 -> 0.5 | M7: =L7 -> 0.5 | ... AC7: =AB7 -> 0.5
B8: Net increase in milk production in the year (million MT*) | E8: =E6*E7*365/1000000000 -> 0.066795 | F8: =F6*F7*365/1000000000 -> 0.1352325 | G8: =G6*G7*365/1000000000 -> 0.21681 | H8: =H6*H7*365/1000000000 -> 0.331785 | I8: =I6*I7*365/1000000000 -> 0.436686 | J8: =J6*J7*365/1000000000 -> 0.496254 | K8: =K6*K7*365/1000000000 -> 0.496254 | L8: =L6*L7*365/1000000000 -> 0.496254 | ... AC8: =AC6*AC7*365/1000000000 -> 0.496254
A10: B | B10: Fodder Seed
B11: Fodder Seed Plants (Nos) | E11: 1 | F11: 2 | G11: 4 | H11: 5 | I11: 6 | J11: 7 | K11: =J11 -> 7 | L11: =K11 -> 7 | M11: =L11 -> 7 | N11: =M11 -> 7 | O11: =N11 -> 7 | P11: =O11 -> 7 | Q11: =P11 -> 7 | R11: =Q11 -> 7 | ... AC11: =AB11 -> 7
B12: Capacity of Fodder Seed Plants (MTD) | E12: 10 | F12: 10 | G12: 10 | H12: 10 | I12: 10 | J12: 10 | K12: 10 | L12: 10 | M12: 10 | N12: 10 | O12: 10 | P12: 10 | Q12: 10 | R12: 10 | S12: 10 | T12: =S12 -> 10 | U12: =T12 -> 10 | V12: =U12 -> 10 | W12: =V12 -> 10 | X12: =W12 -> 10 | Y12: =X12 -> 10 | Z12: =Y12 -> 10 | AA12: =Z12 -> 10 | ... AC12: =AB12 -> 10
B13: Anticipated annual Fodder Seed Production (MT) | E13: 300 | F13: 600 | G13: 1200 | H13: 1500 | I13: 1800 | J13: 2100 | K13: =J13 -> 2100 | L13: =K13 -> 2100 | M13: =L13 -> 2100 | N13: =M13 -> 2100 | O13: =N13 -> 2100 | P13: =O13 -> 2100 | Q13: =P13 -> 2100 | R13: =Q13 -> 2100 | ... AC13: =AB13 -> 2100
B14: Fodder seed required per hactare (Kg) | E14: 50 | F14: 50 | G14: 50 | H14: 50 | I14: 50 | J14: 50 | K14: 50 | L14: 50 | M14: 50 | N14: 50 | O14: 50 | P14: 50 | Q14: 50 | R14: 50 | S14: 50 | T14: =S14 -> 50 | U14: =T14 -> 50 | V14: =U14 -> 50 | W14: =V14 -> 50 | X14: =W14 -> 50 | Y14: =X14 -> 50 | Z14: =Y14 -> 50 | AA14: =Z14 -> 50 | ... AC14: =AB14 -> 50
B15: Total area under fodder seed production (ha) | E15: =E13*1000/E14 -> 6000 | F15: =F13*1000/F14 -> 12000 | G15: =G13*1000/G14 -> 24000 | H15: =H13*1000/H14 -> 30000 | I15: =I13*1000/I14 -> 36000 | J15: =J13*1000/J14 -> 42000 | K15: =K13*1000/K14 -> 42000 | L15: =L13*1000/L14 -> 42000 | ... S15: =S13*1000/S14 -> 42000 | T15: =S15 -> 42000 | U15: =T15 -> 42000 | V15: =U15 -> 42000 | W15: =V15 -> 42000 | X15: =W15 -> 42000 | Y15: =X15 -> 42000 | Z15: =Y15 -> 42000 | AA15: =Z15 -> 42000 | ... AC15: =AB15 -> 42000
B16: Increase in fodder production per hactare (MT) | E16: 40 | F16: 40 | G16: 40 | H16: 40 | I16: 40 | J16: 40 | K16: 40 | L16: 40 | M16: 40 | N16: 40 | O16: 40 | P16: 40 | Q16: 40 | R16: 40 | S16: 40 | T16: =S16 -> 40 | U16: =T16 -> 40 | V16: =U16 -> 40 | W16: =V16 -> 40 | X16: =W16 -> 40 | Y16: =X16 -> 40 | Z16: =Y16 -> 40 | AA16: =Z16 -> 40 | ... AC16: =AB16 -> 40
B17: Annual increase in fodder production (million MT) | E17: =E15*E16/1000000 -> 0.24 | F17: =F15*F16/1000000 -> 0.48 | G17: =G15*G16/1000000 -> 0.96 | H17: =H15*H16/1000000 -> 1.2 | I17: =I15*I16/1000000 -> 1.44 | J17: =J15*J16/1000000 -> 1.68 | K17: =K15*K16/1000000 -> 1.68 | L17: =L15*L16/1000000 -> 1.68 | ... S17: =S15*S16/1000000 -> 1.68 | T17: =S17 -> 1.68 | U17: =T17 -> 1.68 | V17: =U17 -> 1.68 | W17: =V17 -> 1.68 | X17: =W17 -> 1.68 | Y17: =X17 -> 1.68 | Z17: =Y17 -> 1.68 | AA17: =Z17 -> 1.68 | ... AC17: =AB17 -> 1.68
B18: Increase in milk production for every 10 Kg fodder (Kg) | E18: 1 | F18: 1 | G18: 1 | H18: 1 | I18: 1 | J18: 1 | K18: 1 | L18: 1 | M18: 1 | N18: 1 | O18: 1 | P18: 1 | Q18: 1 | R18: 1 | S18: 1 | T18: =S18 -> 1 | U18: =T18 -> 1 | V18: =U18 -> 1 | W18: =V18 -> 1 | X18: =W18 -> 1 | Y18: =X18 -> 1 | Z18: =Y18 -> 1 | AA18: =Z18 -> 1 | ... AC18: =AB18 -> 1
B19: Net increase in milk production in the year (million MT) | E19: =E17*E18/10 -> 0.024 | F19: =F17*F18/10 -> 0.048 | G19: =G17*G18/10 -> 0.096 | H19: =H17*H18/10 -> 0.12 | I19: =I17*I18/10 -> 0.144 | J19: =J17*J18/10 -> 0.168 | K19: =K17*K18/10 -> 0.168 | L19: =L17*L18/10 -> 0.168 | ... S19: =S17*S18/10 -> 0.168 | T19: =S19 -> 0.168 | U19: =T19 -> 0.168 | V19: =U19 -> 0.168 | W19: =V19 -> 0.168 | X19: =W19 -> 0.168 | Y19: =X19 -> 0.168 | Z19: =Y19 -> 0.168 | AA19: =Z19 -> 0.168 | ... AC19: =AB19 -> 0.168
B20: Net increase in milk production in the year ('000 Tonnes) | E20: =E19*1000 -> 24 | F20: =F19*1000 -> 48 | G20: =G19*1000 -> 96 | H20: =H19*1000 -> 120 | I20: =I19*1000 -> 144 | J20: =J19*1000 -> 168 | K20: =K19*1000 -> 168 | L20: =L19*1000 -> 168 | ... S20: =S19*1000 -> 168 | T20: =S20 -> 168 | U20: =T20 -> 168 | V20: =U20 -> 168 | W20: =V20 -> 168 | X20: =W20 -> 168 | Y20: =X20 -> 168 | Z20: =Y20 -> 168 | AA20: =Z20 -> 168 | ... AC20: =AB20 -> 168
A22: C | B22: Straw Densification Plants ( Nos.) | E22: 0 | F22: 1 | G22: 1 | H22: 2 | I22: 2 | J22: 2 | K22: =J22 -> 2 | L22: =K22 -> 2 | M22: =L22 -> 2 | N22: =M22 -> 2 | O22: =N22 -> 2 | P22: =O22 -> 2 | Q22: =P22 -> 2 | R22: =Q22 -> 2 | ... AC22: =AB22 -> 2
B23: Capacity of Straw Densification Plants (MTD) | E23: 40 | F23: 40 | G23: 40 | H23: 40 | I23: 40 | J23: 40 | K23: 40 | L23: 40 | M23: 40 | N23: 40 | O23: 40 | P23: 40 | Q23: 40 | R23: 40 | S23: 40 | T23: 40 | U23: 40 | V23: 40 | W23: 40 | X23: 40 | Y23: 40 | Z23: 40 | AA23: 40 | AB23: 40 | AC23: 40
B24: Anticipated Annual Production (MT) | E24: =E22*E23*300 -> 0 | F24: =F22*F23*300 -> 12000 | G24: =G22*G23*300 -> 12000 | H24: =H22*H23*300 -> 24000 | I24: =I22*I23*300 -> 24000 | J24: =J22*J23*300 -> 24000 | K24: =K22*K23*300 -> 24000 | L24: =L22*L23*300 -> 24000 | ... AC24: =AC22*AC23*300 -> 24000
A25: C | B25: Devt of permanent pasture & common grazing lands
B26: Live Fencing, Plantation, Perennial Grass Seeding, Land and Irrigation Development (Area to be covered) | E26: 400 | F26: 800 | G26: 1200 | H26: 1600 | I26: 2000 | J26: 2800 | K26: =J26 -> 2800 | L26: =K26 -> 2800 | M26: =L26 -> 2800 | N26: =M26 -> 2800 | O26: =N26 -> 2800 | P26: =O26 -> 2800 | Q26: =P26 -> 2800 | R26: =Q26 -> 2800 | ... AC26: =AB26 -> 2800
B27: Incremental Biomass (From 0.75 MT/ hect/yr to 5.75 MT/hect/yr) | E27: =E26*5 -> 2000 | F27: =F26*5 -> 4000 | G27: =G26*5 -> 6000 | H27: =H26*5 -> 8000 | I27: =I26*5 -> 10000 | J27: =J26*5 -> 14000 | K27: =J27 -> 14000 | L27: =K27 -> 14000 | M27: =L27 -> 14000 | N27: =M27 -> 14000 | O27: =N27 -> 14000 | P27: =O27 -> 14000 | Q27: =P27 -> 14000 | R27: =Q27 -> 14000 | ... AC27: =AB27 -> 14000
B28: Annual increase in fodder production (million MT) | E28: =E27/1000000 -> 0.002 | F28: =F27/1000000 -> 0.004 | G28: =G27/1000000 -> 0.006 | H28: =H27/1000000 -> 0.008 | I28: =I27/1000000 -> 0.01 | J28: =J27/1000000 -> 0.014 | K28: =J28 -> 0.014 | L28: =K28 -> 0.014 | M28: =L28 -> 0.014 | N28: =M28 -> 0.014 | O28: =N28 -> 0.014 | P28: =O28 -> 0.014 | Q28: =P28 -> 0.014 | R28: =Q28 -> 0.014 | ... AC28: =AB28 -> 0.014
B29: Increase in milk production for every 10 Kg fodder (Kg) | E29: 1 | F29: 1 | G29: 1 | H29: 1 | I29: 1 | J29: 1 | K29: =J29 -> 1 | L29: =K29 -> 1 | M29: =L29 -> 1 | N29: =M29 -> 1 | O29: =N29 -> 1 | P29: =O29 -> 1 | Q29: =P29 -> 1 | R29: =Q29 -> 1 | ... AC29: =AB29 -> 1
B30: Net increase in milk production in the year (million MT) | E30: =E28*E29/10 -> 0.0002 | F30: =F28*F29/10 -> 0.0004 | G30: =G28*G29/10 -> 0.0006 | H30: =H28*H29/10 -> 0.0008 | I30: =I28*I29/10 -> 0.001 | J30: =J28*J29/10 -> 0.0014 | K30: =J30 -> 0.0014 | L30: =K30 -> 0.0014 | M30: =L30 -> 0.0014 | N30: =M30 -> 0.0014 | O30: =N30 -> 0.0014 | P30: =O30 -> 0.0014 | Q30: =P30 -> 0.0014 | R30: =Q30 -> 0.0014 | ... AC30: =AB30 -> 0.0014
B31: Net increase in milk production in the year ('000 Tonnes) | E31: =E30*1000 -> 0.2 | F31: =F30*1000 -> 0.4 | G31: =G30*1000 -> 0.6 | H31: =H30*1000 -> 0.8 | I31: =I30*1000 -> 1 | J31: =J30*1000 -> 1.4 | K31: =K30*1000 -> 1.4 | L31: =L30*1000 -> 1.4 | ... S31: =S30*1000 -> 1.4 | T31: =S31 -> 1.4 | U31: =T31 -> 1.4 | V31: =U31 -> 1.4 | W31: =V31 -> 1.4 | X31: =W31 -> 1.4 | Y31: =X31 -> 1.4 | Z31: =Y31 -> 1.4 | AA31: =Z31 -> 1.4 | ... AC31: =AB31 -> 1.4
A32: D | B32: Organising Varietal Demonstrations (1/10 of Hect) | E32: 20000 | F32: 40000 | G32: 60000 | H32: 80000 | I32: 100000 | J32: 140000 | K32: =J32 -> 140000 | L32: =K32 -> 140000 | M32: =L32 -> 140000 | N32: =M32 -> 140000 | O32: =N32 -> 140000 | P32: =O32 -> 140000 | Q32: =P32 -> 140000 | R32: =Q32 -> 140000 | ... AC32: =AB32 -> 140000
B33: Villages covered under Varietal Demonstrations (nos.) | E33: =E32/4 -> 5000 | F33: =F32/4 -> 10000 | G33: =G32/4 -> 15000 | H33: =H32/4 -> 20000 | I33: =I32/4 -> 25000 | J33: =J32/4 -> 35000 | K33: =J33 -> 35000 | L33: =K33 -> 35000 | M33: =L33 -> 35000 | N33: =M33 -> 35000 | O33: =N33 -> 35000 | P33: =O33 -> 35000 | Q33: =P33 -> 35000 | R33: =Q33 -> 35000 | ... AC33: =AB33 -> 35000
B34: Villages covered under Varietal Demonstrations (nos.) | E34: =E32/10 -> 2000 | F34: =F32/10 -> 4000 | G34: =G32/10 -> 6000 | H34: =H32/10 -> 8000 | I34: =I32/10 -> 10000 | J34: =J32/10 -> 14000 | K34: =J34 -> 14000 | L34: =K34 -> 14000 | M34: =L34 -> 14000 | N34: =M34 -> 14000 | O34: =N34 -> 14000 | P34: =O34 -> 14000 | Q34: =P34 -> 14000 | R34: =Q34 -> 14000 | ... AC34: =AB34 -> 14000
B35: Increase in fodder production per hactare (MT) | E35: 40 | F35: 40 | G35: 40 | H35: 40 | I35: 40 | J35: 40 | K35: 40 | L35: =K35 -> 40 | M35: =L35 -> 40 | N35: =M35 -> 40 | O35: =N35 -> 40 | P35: =O35 -> 40 | Q35: =P35 -> 40 | R35: =Q35 -> 40 | S35: =R35 -> 40 | ... AC35: =AB35 -> 40
B36: Annual increase in fodder production (million MT) | E36: =E34*E35/1000000 -> 0.08 | F36: =F34*F35/1000000 -> 0.16 | G36: =G34*G35/1000000 -> 0.24 | H36: =H34*H35/1000000 -> 0.32 | I36: =I34*I35/1000000 -> 0.4 | J36: =J34*J35/1000000 -> 0.56 | K36: =K34*K35/1000000 -> 0.56 | L36: =K36 -> 0.56 | M36: =L36 -> 0.56 | N36: =M36 -> 0.56 | O36: =N36 -> 0.56 | P36: =O36 -> 0.56 | Q36: =P36 -> 0.56 | R36: =Q36 -> 0.56 | S36: =R36 -> 0.56 | ... AC36: =AB36 -> 0.56
B37: Increase in milk production for every 10 Kg fodder (Kg) | E37: 1 | F37: 1 | G37: 1 | H37: 1 | I37: 1 | J37: 1 | K37: =J37 -> 1 | L37: =K37 -> 1 | M37: =L37 -> 1 | N37: =M37 -> 1 | O37: =N37 -> 1 | P37: =O37 -> 1 | Q37: =P37 -> 1 | R37: =Q37 -> 1 | ... AC37: =AB37 -> 1
B38: Net increase in milk production in the year (million MT) | E38: =E36*E37/10 -> 0.008 | F38: =F36*F37/10 -> 0.016 | G38: =G36*G37/10 -> 0.024 | H38: =H36*H37/10 -> 0.032 | I38: =I36*I37/10 -> 0.04 | J38: =J36*J37/10 -> 0.056 | K38: =J38 -> 0.056 | L38: =K38 -> 0.056 | M38: =L38 -> 0.056 | N38: =M38 -> 0.056 | O38: =N38 -> 0.056 | P38: =O38 -> 0.056 | Q38: =P38 -> 0.056 | R38: =Q38 -> 0.056 | ... AC38: =AB38 -> 0.056
B39: Net increase in milk production in the year ('000 Tonnes) | E39: =E38*1000 -> 8 | F39: =F38*1000 -> 16 | G39: =G38*1000 -> 24 | H39: =H38*1000 -> 32 | I39: =I38*1000 -> 40 | J39: =J38*1000 -> 56 | K39: =K38*1000 -> 56 | L39: =L38*1000 -> 56 | ... S39: =S38*1000 -> 56 | T39: =S39 -> 56 | U39: =T39 -> 56 | V39: =U39 -> 56 | W39: =V39 -> 56 | X39: =W39 -> 56 | Y39: =X39 -> 56 | Z39: =Y39 -> 56 | AA39: =Z39 -> 56 | ... AC39: =AB39 -> 56
B41: Weighted average milk yield, Kg/day | C41: =+C59*1.03 -> 4.6587415
B42: Milk Productivity with RBP Intervention (Kg/day/animal), Incremental | C42: =+C41*E59 -> 0.46587415
B43: Milk Poduction with RBP intervention (Million tonnes), Incremental | C43: Million Tonnes | E43: 0 | F43: =$C$42*E6*365/1000000000 -> 0.062236128 | G43: =$C$42*F6*365/1000000000 -> 0.12600265 | H43: =$C$42*G6*365/1000000000 -> 0.20201235 | I43: =$C$42*H6*365/1000000000 -> 0.30914011 | J43: =$C$42*I6*365/1000000000 -> 0.40688144 | K43: =$C$42*J6*365/1000000000 -> 0.46238382 | L43: =$C$42*K6*365/1000000000 -> 0.46238382 | M43: =$C$42*L6*365/1000000000 -> 0.46238382 | ... AC43: =$C$42*AB6*365/1000000000 -> 0.46238382
B44: Quantity of Additional Fat Produced with RBP (Million tonnes) | C44: ='Feed and Fodder'!S4 -> 0.0025 | E44: =$C$44*E43 -> 0 | F44: =$C$44*F43 -> 0.00015559032 | G44: =$C$44*G43 -> 0.00031500663 | H44: =$C$44*H43 -> 0.00050503087 | I44: =$C$44*I43 -> 0.00077285027 | J44: =$C$44*J43 -> 0.0010172036 | K44: =$C$44*K43 -> 0.0011559596 | L44: =$C$44*L43 -> 0.0011559596 | ... AC44: =$C$44*AC43 -> 0.0011559596
B45: Reduction in Feeding Cost | C45: Million Rupees | E45: 0 | F45: =+$C$71*$C$41*E6*365/1000000 -> 364.67776 | G45: =+$C$71*$C$41*F6*365/1000000 -> 738.323 | H45: =+$C$71*$C$41*G6*365/1000000 -> 1183.7081 | I45: =+$C$71*$C$41*H6*365/1000000 -> 1811.4321 | J45: =+$C$71*$C$41*I6*365/1000000 -> 2384.1556 | K45: =+$C$71*$C$41*J6*365/1000000 -> 2709.3764 | L45: =+$C$71*$C$41*K6*365/1000000 -> 2709.3764 | M45: =+$C$71*$C$41*L6*365/1000000 -> 2709.3764 | ... AC45: =+$C$71*$C$41*AB6*365/1000000 -> 2709.3764
B47: Reduction in Methane Emissions (CER units per annum) | C47: ='Feed and Fodder'!D33 -> 0.16453421 | E47: 0 | F47: =$C$47*E6 -> 60219.522 | G47: =$C$47*F6 -> 121919.85 | H47: =$C$47*G6 -> 195466.64 | I47: =$C$47*H6 -> 299123.2 | J47: =$C$47*I6 -> 393697.46 | K47: =$C$47*J6 -> 447401.43 | L47: =$C$47*K6 -> 447401.43 | M47: =$C$47*L6 -> 447401.43 | ... AC47: =$C$47*AB6 -> 447401.43
B48: Benefit due to reduction in Methane Emissions ( Rs million per annum) | C48: ='Feed and Fodder'!C34 -> 740 | E48: =E47*$C$48/1000000 -> 0 | F48: =F47*$C$48/1000000 -> 44.562446 | G48: =G47*$C$48/1000000 -> 90.22069 | H48: =H47*$C$48/1000000 -> 144.64532 | I48: =I47*$C$48/1000000 -> 221.35117 | J48: =J47*$C$48/1000000 -> 291.33612 | K48: =K47*$C$48/1000000 -> 331.07706 | L48: =L47*$C$48/1000000 -> 331.07706 | ... AC48: =AC47*$C$48/1000000 -> 331.07706
B50: Benefit due to increase in milk productivity (Rs Million pe annum) | E50: =+E43*$G$62 -> 0 | F50: =+F43*$G$62 -> 190.70142 | G50: =+G43*$G$62 -> 386.09222 | H50: =+H43*$G$62 -> 618.99806 | I50: =+I43*$G$62 -> 947.25461 | J50: =+J43*$G$62 -> 1246.7496 | K50: =+K43*$G$62 -> 1416.8178 | L50: =+L43*$G$62 -> 1416.8178 | ... AC50: =+AC43*$G$62 -> 1416.8178
B52: Total Benefits from RBP Programme | E52: =+SUM(E45,E48,E50) -> 0 | F52: =+SUM(F45,F48,F50) -> 599.94162 | G52: =+SUM(G45,G48,G50) -> 1214.6359 | H52: =+SUM(H45,H48,H50) -> 1947.3515 | I52: =+SUM(I45,I48,I50) -> 2980.0379 | J52: =+SUM(J45,J48,J50) -> 3922.2413 | K52: =+SUM(K45,K48,K50) -> 4457.2712 | L52: =+SUM(L45,L48,L50) -> 4457.2712 | ... AC52: =+SUM(AC45,AC48,AC50) -> 4457.2712
B55: Assumptions : | D55: =+D59*E59 -> 165.09132
J56: =+C57*C42 -> 170.04406
B57: Number of days in lactation considered | C57: 365 | D57: 1438 | E57: =+G59/D57 -> 0.11480621 | G57: Incremental | J57: =+J56*1.03 -> 175.14539 | K57: =+J57/1000 -> 0.17514539
G58: Lactn Yield, L | J58: =+J57*J6 -> 4.7625534e+08 | K58: =+K57*2.94 -> 0.51492744
B59: Average Mik yield ( l/day) | C59: ='Feed and Fodder (F) Zone.2'!$C$59 -> 4.52305 | D59: =+C59*C57 -> 1650.9132 | E59: 0.1 | G59: =+C59*C57*E59 -> 165.09132
C60: l/day | E60: Proportion Considered
B61: Indigenous cows | C61: 2.136 | E61: 0.35 | G61: Financial Gross Margin | I61: Rs/MT | K61: =+G59*'Feed and Fodder (E) Zone.2'!J99+'Feed and Fodder (E) Zone.2'!J98*'Feed and Fodder (F) Zone.2'!G59 -> 165.09132
B62: Cross Breds | C62: 6.869 | E62: 0.35 | G62: 3064.1595
B63: buffaloes | C63: 4.571 | E63: ='Feed and Fodder'!C25 -> 0.3
G65: Financial Production Cost | I65: Rs/Kg
B66: Unit Prodn Cost, Rs/Kg | C66: =+G66 -> 16.741666 | G66: 16.741666
B67: Feed and Fodder Cost, % | C67: 0.7
B68: Feed and Fodder Cost, Rs/Kg | C68: =+C66*C67 -> 11.719166
B70: Reduction in Feed and Fodder Cost, % | C70: 0.05
B71: Savings in Feed and Fodder Cost, Rs/Kg | C71: =+C68*C70 -> 0.5859583 | D71: =+C71/C66 -> 0.035 | E71: =+C71*E6*C41 -> 999117.14 | G71: =+C71/C66 -> 0.035
C75: 1 | E75: Yr-1 | F75: Yr-2 | G75: Yr-3 | H75: Yr-4 | I75: Yr-5 | J75: Yr-6 | K75: Yr-7 | L75: Yr-8 | M75: Yr-9 | N75: Yr-10 | O75: Yr-11 | P75: Yr-12 | Q75: Yr-13 | R75: Yr-14 | S75: Yr-15 | T75: Yr-16 | U75: Yr-17 | V75: Yr-18 | W75: Yr-19 | X75: Yr-20 | Y75: Yr-21 | Z75: Yr-22 | AA75: Yr-23 | AB75: Yr-24 | AC75: Yr-25 | AD75: Yr-26
B76: For EFA Analysis | C76: Adopters | E76: 0 | F76: 0 | G76: 0.25 | H76: 0.5 | I76: 0.75 | J76: 1 | K76: 1 | L76: 1 | M76: 1 | N76: 1 | O76: 1 | P76: 1 | Q76: 1 | R76: 1 | S76: 1 | T76: 1 | U76: 1 | V76: 1 | W76: 1 | X76: 1 | Y76: 1 | Z76: 1 | AA76: 1 | AB76: 1 | AC76: 1 | AD76: 1
C77: 0.05 | E77: =+$C77*E76*$C$75 -> 0 | F77: =+$C77*F76*$C$75 -> 0 | G77: =+$C77*G76*$C$75 -> 0.0125 | H77: =+$C77*H76*$C$75 -> 0.025 | I77: =+$C77*I76*$C$75 -> 0.0375 | J77: =+$C77*J76*$C$75 -> 0.05 | K77: =+$C77*K76*$C$75 -> 0.05 | L77: =+$C77*L76*$C$75 -> 0.05 | ... AD77: =+$C77*AD76*$C$75 -> 0.05
C78: 0.1 | F78: =+$C78*E76*$C$75 -> 0 | G78: =+$C78*F76*$C$75 -> 0 | H78: =+$C78*G76*$C$75 -> 0.025 | I78: =+$C78*H76*$C$75 -> 0.05 | J78: =+$C78*I76*$C$75 -> 0.075 | K78: =+$C78*J76*$C$75 -> 0.1 | L78: =+$C78*K76*$C$75 -> 0.1 | M78: =+$C78*L76*$C$75 -> 0.1 | ... AD78: =+$C78*AC76*$C$75 -> 0.1
C79: 0.2 | G79: =+$C79*E76*$C$75 -> 0 | H79: =+$C79*F76*$C$75 -> 0 | I79: =+$C79*G76*$C$75 -> 0.05 | J79: =+$C79*H76*$C$75 -> 0.1 | K79: =+$C79*I76*$C$75 -> 0.15 | L79: =+$C79*J76*$C$75 -> 0.2 | M79: =+$C79*K76*$C$75 -> 0.2 | N79: =+$C79*L76*$C$75 -> 0.2 | ... AD79: =+$C79*AB76*$C$75 -> 0.2
C80: 0.25 | H80: =+$C80*E76*$C$75 -> 0 | I80: =+$C80*F76*$C$75 -> 0 | J80: =+$C80*G76*$C$75 -> 0.0625 | K80: =+$C80*H76*$C$75 -> 0.125 | L80: =+$C80*I76*$C$75 -> 0.1875 | M80: =+$C80*J76*$C$75 -> 0.25 | N80: =+$C80*K76*$C$75 -> 0.25 | O80: =+$C80*L76*$C$75 -> 0.25 | ... AD80: =+$C80*AA76*$C$75 -> 0.25
C81: 0.3 | I81: =+$C81*E76*$C$75 -> 0 | J81: =+$C81*F76*$C$75 -> 0 | K81: =+$C81*G76*$C$75 -> 0.075 | L81: =+$C81*H76*$C$75 -> 0.15 | M81: =+$C81*I76*$C$75 -> 0.225 | N81: =+$C81*J76*$C$75 -> 0.3 | O81: =+$C81*K76*$C$75 -> 0.3 | P81: =+$C81*L76*$C$75 -> 0.3 | ... AD81: =+$C81*Z76*$C$75 -> 0.3
C82: 0.1 | J82: =+$C82*E76*$C$75 -> 0 | K82: =+$C82*F76*$C$75 -> 0 | L82: =+$C82*G76*$C$75 -> 0.025 | M82: =+$C82*H76*$C$75 -> 0.05 | N82: =+$C82*I76*$C$75 -> 0.075 | O82: =+$C82*J76*$C$75 -> 0.1 | P82: =+$C82*K76*$C$75 -> 0.1 | Q82: =+$C82*L76*$C$75 -> 0.1 | ... AD82: =+$C82*Y76*$C$75 -> 0.1
C83: =+SUM(C77:C82) -> 1 | E83: =SUM(E77:E82) -> 0 | F83: =SUM(F77:F82) -> 0 | G83: =SUM(G77:G82) -> 0.0125 | H83: =SUM(H77:H82) -> 0.05 | I83: =SUM(I77:I82) -> 0.1375 | J83: =SUM(J77:J82) -> 0.2875 | K83: =SUM(K77:K82) -> 0.5 | L83: =SUM(L77:L82) -> 0.7125 | ... AD83: =SUM(AD77:AD82) -> 1
B84: Zone-1
C85: 0.5
B86: =+B45 -> Reduction in Feeding Cost | E86: =+E$83*E45*$C$85 -> 0 | F86: =+F$83*F45*$C$85 -> 0 | G86: =+G$83*G45*$C$85 -> 4.6145187 | H86: =+H$83*H45*$C$85 -> 29.592703 | I86: =+I$83*I45*$C$85 -> 124.53596 | J86: =+J$83*J45*$C$85 -> 342.72236 | K86: =+K$83*K45*$C$85 -> 677.34409 | L86: =+L$83*L45*$C$85 -> 965.21534 | ... AD86: =+AD$83*AD45*$C$85 -> 0 | AF86: =+AC86/SUM($AC$86:$AC$90) -> 0.6078554
B88: =+B48 -> Benefit due to reduction in Methane Emissions ( Rs million per annum) | E88: =+E$83*E48*$C$85 -> 0 | F88: =+F$83*F48*$C$85 -> 0 | G88: =+G$83*G48*$C$85 -> 0.56387931 | H88: =+H$83*H48*$C$85 -> 3.6161329 | I88: =+I$83*I48*$C$85 -> 15.217893 | J88: =+J$83*J48*$C$85 -> 41.879568 | K88: =+K$83*K48*$C$85 -> 82.769265 | L88: =+L$83*L48*$C$85 -> 117.9462 | ... AD88: =+AD$83*AD48*$C$85 -> 0 | AF88: =+AC88/SUM($AC$86:$AC$90) -> 0.07427797
B90: =+B50 -> Benefit due to increase in milk productivity (Rs Million pe annum) | E90: =+E$83*E50*$C$85 -> 0 | F90: =+F$83*F50*$C$85 -> 0 | G90: =+G$83*G50*$C$85 -> 2.4130764 | H90: =+H$83*H50*$C$85 -> 15.474951 | I90: =+I$83*I50*$C$85 -> 65.123754 | J90: =+J$83*J50*$C$85 -> 179.22026 | K90: =+K$83*K50*$C$85 -> 354.20445 | L90: =+L$83*L50*$C$85 -> 504.74133 | ... AD90: =+AD$83*AD50*$C$85 -> 0 | AF90: =+AC90/SUM($AC$86:$AC$90) -> 0.31786663
AC92: =+SUM(AC86:AC90) -> 2228.6356
W94: =1417+W86 -> 2771.6882

Sheet Feed and Fodder (F) Zone.2
A1: Contribution of Feed & Nutrition to Additional Milk Production
C2: Current | E2: 2011-12 | F2: 2012-13 | G2: 2013-14 | H2: 2014-15 | I2: 2015-16 | J2: 2016-17 | K2: 2017-18 | L2: 2018-19 | M2: 2019-20 | N2: 2020-21 | O2: 2021-22 | P2: 2022-23 | Q2: 2023-24 | R2: 2024-25 | S2: 2025-26 | T2: 2026-27 | U2: 2027-28 | V2: 2028-29 | W2: 2029-30 | X2: 2030-31 | Y2: 2031-32 | Z2: 2032-33 | AA2: 2033-34 | AB2: 2034-35 | AC2: 2036-37
A3: A. | B3: Ration Balancing Programme RBP
B4: PDAs (Nos.) | C4: 25 | E4: 830 | F4: 1270 | G4: 730 | H4: 730 | I4: 1630 | J4: 2010 | K4: =J4 -> 2010 | L4: =K4 -> 2010 | M4: =L4 -> 2010 | N4: =M4 -> 2010 | O4: =N4 -> 2010 | P4: =O4 -> 2010 | Q4: =P4 -> 2010 | R4: =Q4 -> 2010 | S4: =R4 -> 2010
B5: Villages (Nos) | E5: 5500 | F5: 11100 | G5: 17700 | H5: 27300 | I5: 35880 | J5: 40320 | K5: 40320 | L5: 40320 | M5: 40320 | N5: 40320 | O5: 40320 | P5: 40320 | Q5: 40320 | R5: 40320 | S5: 40320 | T5: 40320 | U5: 40320 | V5: 40320 | W5: 40320 | X5: 40320 | Y5: 40320 | Z5: 40320 | AA5: 40320 | AB5: 40320 | AC5: 40320
B6: Animals covered (Nos) | E6: 366000 | F6: 741000 | G6: 1188000 | H6: 1818000 | I6: 2392800 | J6: 2719200 | K6: 2719200 | L6: 2719200 | M6: 2719200 | N6: 2719200 | O6: 2719200 | P6: 2719200 | Q6: 2719200 | R6: 2719200 | S6: 2719200 | T6: 2719200 | U6: 2719200 | V6: 2719200 | W6: 2719200 | X6: 2719200 | Y6: 2719200 | Z6: 2719200 | AA6: 2719200 | AB6: 2719200 | AC6: 2719200
B7: Average increase in milk production due to the programme (KgPD/Animal) | E7: ='Feed and Fodder'!S14 -> 0.5 | F7: =E7 -> 0.5 | G7: =F7 -> 0.5 | H7: =G7 -> 0.5 | I7: =H7 -> 0.5 | J7: =I7 -> 0.5 | K7: =J7 -> 0.5 | L7: =K7 -> 0.5 | M7: =L7 -> 0.5 | ... AC7: =AB7 -> 0.5
B8: Net increase in milk production in the year (million MT*) | E8: =E6*E7*365/1000000000 -> 0.066795 | F8: =F6*F7*365/1000000000 -> 0.1352325 | G8: =G6*G7*365/1000000000 -> 0.21681 | H8: =H6*H7*365/1000000000 -> 0.331785 | I8: =I6*I7*365/1000000000 -> 0.436686 | J8: =J6*J7*365/1000000000 -> 0.496254 | K8: =K6*K7*365/1000000000 -> 0.496254 | L8: =L6*L7*365/1000000000 -> 0.496254 | ... AC8: =AC6*AC7*365/1000000000 -> 0.496254
A10: B | B10: Fodder Seed
B11: Fodder Seed Plants (Nos) | E11: 1 | F11: 2 | G11: 4 | H11: 5 | I11: 6 | J11: 7 | K11: =J11 -> 7 | L11: =K11 -> 7 | M11: =L11 -> 7 | N11: =M11 -> 7 | O11: =N11 -> 7 | P11: =O11 -> 7 | Q11: =P11 -> 7 | R11: =Q11 -> 7 | ... AC11: =AB11 -> 7
B12: Capacity of Fodder Seed Plants (MTD) | E12: 10 | F12: 10 | G12: 10 | H12: 10 | I12: 10 | J12: 10 | K12: 10 | L12: 10 | M12: 10 | N12: 10 | O12: 10 | P12: 10 | Q12: 10 | R12: 10 | S12: 10 | T12: =S12 -> 10 | U12: =T12 -> 10 | V12: =U12 -> 10 | W12: =V12 -> 10 | X12: =W12 -> 10 | Y12: =X12 -> 10 | Z12: =Y12 -> 10 | AA12: =Z12 -> 10 | ... AC12: =AB12 -> 10
B13: Anticipated annual Fodder Seed Production (MT) | E13: 300 | F13: 600 | G13: 1200 | H13: 1500 | I13: 1800 | J13: 2100 | K13: =J13 -> 2100 | L13: =K13 -> 2100 | M13: =L13 -> 2100 | N13: =M13 -> 2100 | O13: =N13 -> 2100 | P13: =O13 -> 2100 | Q13: =P13 -> 2100 | R13: =Q13 -> 2100 | ... AC13: =AB13 -> 2100
B14: Fodder seed required per hactare (Kg) | E14: 50 | F14: 50 | G14: 50 | H14: 50 | I14: 50 | J14: 50 | K14: 50 | L14: 50 | M14: 50 | N14: 50 | O14: 50 | P14: 50 | Q14: 50 | R14: 50 | S14: 50 | T14: =S14 -> 50 | U14: =T14 -> 50 | V14: =U14 -> 50 | W14: =V14 -> 50 | X14: =W14 -> 50 | Y14: =X14 -> 50 | Z14: =Y14 -> 50 | AA14: =Z14 -> 50 | ... AC14: =AB14 -> 50
B15: Total area under fodder seed production (ha) | E15: =E13*1000/E14 -> 6000 | F15: =F13*1000/F14 -> 12000 | G15: =G13*1000/G14 -> 24000 | H15: =H13*1000/H14 -> 30000 | I15: =I13*1000/I14 -> 36000 | J15: =J13*1000/J14 -> 42000 | K15: =K13*1000/K14 -> 42000 | L15: =L13*1000/L14 -> 42000 | ... S15: =S13*1000/S14 -> 42000 | T15: =S15 -> 42000 | U15: =T15 -> 42000 | V15: =U15 -> 42000 | W15: =V15 -> 42000 | X15: =W15 -> 42000 | Y15: =X15 -> 42000 | Z15: =Y15 -> 42000 | AA15: =Z15 -> 42000 | ... AC15: =AB15 -> 42000
B16: Increase in fodder production per hactare (MT) | E16: 40 | F16: 40 | G16: 40 | H16: 40 | I16: 40 | J16: 40 | K16: 40 | L16: 40 | M16: 40 | N16: 40 | O16: 40 | P16: 40 | Q16: 40 | R16: 40 | S16: 40 | T16: =S16 -> 40 | U16: =T16 -> 40 | V16: =U16 -> 40 | W16: =V16 -> 40 | X16: =W16 -> 40 | Y16: =X16 -> 40 | Z16: =Y16 -> 40 | AA16: =Z16 -> 40 | ... AC16: =AB16 -> 40
B17: Annual increase in fodder production (million MT) | E17: =E15*E16/1000000 -> 0.24 | F17: =F15*F16/1000000 -> 0.48 | G17: =G15*G16/1000000 -> 0.96 | H17: =H15*H16/1000000 -> 1.2 | I17: =I15*I16/1000000 -> 1.44 | J17: =J15*J16/1000000 -> 1.68 | K17: =K15*K16/1000000 -> 1.68 | L17: =L15*L16/1000000 -> 1.68 | ... S17: =S15*S16/1000000 -> 1.68 | T17: =S17 -> 1.68 | U17: =T17 -> 1.68 | V17: =U17 -> 1.68 | W17: =V17 -> 1.68 | X17: =W17 -> 1.68 | Y17: =X17 -> 1.68 | Z17: =Y17 -> 1.68 | AA17: =Z17 -> 1.68 | ... AC17: =AB17 -> 1.68
B18: Increase in milk production for every 10 Kg fodder (Kg) | E18: 1 | F18: 1 | G18: 1 | H18: 1 | I18: 1 | J18: 1 | K18: 1 | L18: 1 | M18: 1 | N18: 1 | O18: 1 | P18: 1 | Q18: 1 | R18: 1 | S18: 1 | T18: =S18 -> 1 | U18: =T18 -> 1 | V18: =U18 -> 1 | W18: =V18 -> 1 | X18: =W18 -> 1 | Y18: =X18 -> 1 | Z18: =Y18 -> 1 | AA18: =Z18 -> 1 | ... AC18: =AB18 -> 1
B19: Net increase in milk production in the year (million MT) | E19: =E17*E18/10 -> 0.024 | F19: =F17*F18/10 -> 0.048 | G19: =G17*G18/10 -> 0.096 | H19: =H17*H18/10 -> 0.12 | I19: =I17*I18/10 -> 0.144 | J19: =J17*J18/10 -> 0.168 | K19: =K17*K18/10 -> 0.168 | L19: =L17*L18/10 -> 0.168 | ... S19: =S17*S18/10 -> 0.168 | T19: =S19 -> 0.168 | U19: =T19 -> 0.168 | V19: =U19 -> 0.168 | W19: =V19 -> 0.168 | X19: =W19 -> 0.168 | Y19: =X19 -> 0.168 | Z19: =Y19 -> 0.168 | AA19: =Z19 -> 0.168 | ... AC19: =AB19 -> 0.168
B20: Net increase in milk production in the year ('000 Tonnes) | E20: =E19*1000 -> 24 | F20: =F19*1000 -> 48 | G20: =G19*1000 -> 96 | H20: =H19*1000 -> 120 | I20: =I19*1000 -> 144 | J20: =J19*1000 -> 168 | K20: =K19*1000 -> 168 | L20: =L19*1000 -> 168 | ... S20: =S19*1000 -> 168 | T20: =S20 -> 168 | U20: =T20 -> 168 | V20: =U20 -> 168 | W20: =V20 -> 168 | X20: =W20 -> 168 | Y20: =X20 -> 168 | Z20: =Y20 -> 168 | AA20: =Z20 -> 168 | ... AC20: =AB20 -> 168
A22: C | B22: Straw Densification Plants ( Nos.) | E22: 0 | F22: 1 | G22: 1 | H22: 2 | I22: 2 | J22: 2 | K22: =J22 -> 2 | L22: =K22 -> 2 | M22: =L22 -> 2 | N22: =M22 -> 2 | O22: =N22 -> 2 | P22: =O22 -> 2 | Q22: =P22 -> 2 | R22: =Q22 -> 2 | ... AC22: =AB22 -> 2
B23: Capacity of Straw Densification Plants (MTD) | E23: 40 | F23: 40 | G23: 40 | H23: 40 | I23: 40 | J23: 40 | K23: 40 | L23: 40 | M23: 40 | N23: 40 | O23: 40 | P23: 40 | Q23: 40 | R23: 40 | S23: 40 | T23: 40 | U23: 40 | V23: 40 | W23: 40 | X23: 40 | Y23: 40 | Z23: 40 | AA23: 40 | AB23: 40 | AC23: 40
B24: Anticipated Annual Production (MT) | E24: =E22*E23*300 -> 0 | F24: =F22*F23*300 -> 12000 | G24: =G22*G23*300 -> 12000 | H24: =H22*H23*300 -> 24000 | I24: =I22*I23*300 -> 24000 | J24: =J22*J23*300 -> 24000 | K24: =K22*K23*300 -> 24000 | L24: =L22*L23*300 -> 24000 | ... AC24: =AC22*AC23*300 -> 24000
A25: C | B25: Devt of permanent pasture & common grazing lands
B26: Live Fencing, Plantation, Perennial Grass Seeding, Land and Irrigation Development (Area to be covered) | E26: 400 | F26: 800 | G26: 1200 | H26: 1600 | I26: 2000 | J26: 2800 | K26: =J26 -> 2800 | L26: =K26 -> 2800 | M26: =L26 -> 2800 | N26: =M26 -> 2800 | O26: =N26 -> 2800 | P26: =O26 -> 2800 | Q26: =P26 -> 2800 | R26: =Q26 -> 2800 | ... AC26: =AB26 -> 2800
B27: Incremental Biomass (From 0.75 MT/ hect/yr to 5.75 MT/hect/yr) | E27: =E26*5 -> 2000 | F27: =F26*5 -> 4000 | G27: =G26*5 -> 6000 | H27: =H26*5 -> 8000 | I27: =I26*5 -> 10000 | J27: =J26*5 -> 14000 | K27: =J27 -> 14000 | L27: =K27 -> 14000 | M27: =L27 -> 14000 | N27: =M27 -> 14000 | O27: =N27 -> 14000 | P27: =O27 -> 14000 | Q27: =P27 -> 14000 | R27: =Q27 -> 14000 | ... AC27: =AB27 -> 14000
B28: Annual increase in fodder production (million MT) | E28: =E27/1000000 -> 0.002 | F28: =F27/1000000 -> 0.004 | G28: =G27/1000000 -> 0.006 | H28: =H27/1000000 -> 0.008 | I28: =I27/1000000 -> 0.01 | J28: =J27/1000000 -> 0.014 | K28: =J28 -> 0.014 | L28: =K28 -> 0.014 | M28: =L28 -> 0.014 | N28: =M28 -> 0.014 | O28: =N28 -> 0.014 | P28: =O28 -> 0.014 | Q28: =P28 -> 0.014 | R28: =Q28 -> 0.014 | ... AC28: =AB28 -> 0.014
B29: Increase in milk production for every 10 Kg fodder (Kg) | E29: 1 | F29: 1 | G29: 1 | H29: 1 | I29: 1 | J29: 1 | K29: =J29 -> 1 | L29: =K29 -> 1 | M29: =L29 -> 1 | N29: =M29 -> 1 | O29: =N29 -> 1 | P29: =O29 -> 1 | Q29: =P29 -> 1 | R29: =Q29 -> 1 | ... AC29: =AB29 -> 1
B30: Net increase in milk production in the year (million MT) | E30: =E28*E29/10 -> 0.0002 | F30: =F28*F29/10 -> 0.0004 | G30: =G28*G29/10 -> 0.0006 | H30: =H28*H29/10 -> 0.0008 | I30: =I28*I29/10 -> 0.001 | J30: =J28*J29/10 -> 0.0014 | K30: =J30 -> 0.0014 | L30: =K30 -> 0.0014 | M30: =L30 -> 0.0014 | N30: =M30 -> 0.0014 | O30: =N30 -> 0.0014 | P30: =O30 -> 0.0014 | Q30: =P30 -> 0.0014 | R30: =Q30 -> 0.0014 | ... AC30: =AB30 -> 0.0014
B31: Net increase in milk production in the year ('000 Tonnes) | E31: =E30*1000 -> 0.2 | F31: =F30*1000 -> 0.4 | G31: =G30*1000 -> 0.6 | H31: =H30*1000 -> 0.8 | I31: =I30*1000 -> 1 | J31: =J30*1000 -> 1.4 | K31: =K30*1000 -> 1.4 | L31: =L30*1000 -> 1.4 | ... S31: =S30*1000 -> 1.4 | T31: =S31 -> 1.4 | U31: =T31 -> 1.4 | V31: =U31 -> 1.4 | W31: =V31 -> 1.4 | X31: =W31 -> 1.4 | Y31: =X31 -> 1.4 | Z31: =Y31 -> 1.4 | AA31: =Z31 -> 1.4 | ... AC31: =AB31 -> 1.4
A32: D | B32: Organising Varietal Demonstrations (1/10 of Hect) | E32: 20000 | F32: 40000 | G32: 60000 | H32: 80000 | I32: 100000 | J32: 140000 | K32: =J32 -> 140000 | L32: =K32 -> 140000 | M32: =L32 -> 140000 | N32: =M32 -> 140000 | O32: =N32 -> 140000 | P32: =O32 -> 140000 | Q32: =P32 -> 140000 | R32: =Q32 -> 140000 | ... AC32: =AB32 -> 140000
B33: Villages covered under Varietal Demonstrations (nos.) | E33: =E32/4 -> 5000 | F33: =F32/4 -> 10000 | G33: =G32/4 -> 15000 | H33: =H32/4 -> 20000 | I33: =I32/4 -> 25000 | J33: =J32/4 -> 35000 | K33: =J33 -> 35000 | L33: =K33 -> 35000 | M33: =L33 -> 35000 | N33: =M33 -> 35000 | O33: =N33 -> 35000 | P33: =O33 -> 35000 | Q33: =P33 -> 35000 | R33: =Q33 -> 35000 | ... AC33: =AB33 -> 35000
B34: Villages covered under Varietal Demonstrations (nos.) | E34: =E32/10 -> 2000 | F34: =F32/10 -> 4000 | G34: =G32/10 -> 6000 | H34: =H32/10 -> 8000 | I34: =I32/10 -> 10000 | J34: =J32/10 -> 14000 | K34: =J34 -> 14000 | L34: =K34 -> 14000 | M34: =L34 -> 14000 | N34: =M34 -> 14000 | O34: =N34 -> 14000 | P34: =O34 -> 14000 | Q34: =P34 -> 14000 | R34: =Q34 -> 14000 | ... AC34: =AB34 -> 14000
B35: Increase in fodder production per hactare (MT) | E35: 40 | F35: 40 | G35: 40 | H35: 40 | I35: 40 | J35: 40 | K35: 40 | L35: =K35 -> 40 | M35: =L35 -> 40 | N35: =M35 -> 40 | O35: =N35 -> 40 | P35: =O35 -> 40 | Q35: =P35 -> 40 | R35: =Q35 -> 40 | S35: =R35 -> 40 | ... AC35: =AB35 -> 40
B36: Annual increase in fodder production (million MT) | E36: =E34*E35/1000000 -> 0.08 | F36: =F34*F35/1000000 -> 0.16 | G36: =G34*G35/1000000 -> 0.24 | H36: =H34*H35/1000000 -> 0.32 | I36: =I34*I35/1000000 -> 0.4 | J36: =J34*J35/1000000 -> 0.56 | K36: =K34*K35/1000000 -> 0.56 | L36: =K36 -> 0.56 | M36: =L36 -> 0.56 | N36: =M36 -> 0.56 | O36: =N36 -> 0.56 | P36: =O36 -> 0.56 | Q36: =P36 -> 0.56 | R36: =Q36 -> 0.56 | S36: =R36 -> 0.56 | ... AC36: =AB36 -> 0.56
B37: Increase in milk production for every 10 Kg fodder (Kg) | E37: 1 | F37: 1 | G37: 1 | H37: 1 | I37: 1 | J37: 1 | K37: =J37 -> 1 | L37: =K37 -> 1 | M37: =L37 -> 1 | N37: =M37 -> 1 | O37: =N37 -> 1 | P37: =O37 -> 1 | Q37: =P37 -> 1 | R37: =Q37 -> 1 | ... AC37: =AB37 -> 1
B38: Net increase in milk production in the year (million MT) | E38: =E36*E37/10 -> 0.008 | F38: =F36*F37/10 -> 0.016 | G38: =G36*G37/10 -> 0.024 | H38: =H36*H37/10 -> 0.032 | I38: =I36*I37/10 -> 0.04 | J38: =J36*J37/10 -> 0.056 | K38: =J38 -> 0.056 | L38: =K38 -> 0.056 | M38: =L38 -> 0.056 | N38: =M38 -> 0.056 | O38: =N38 -> 0.056 | P38: =O38 -> 0.056 | Q38: =P38 -> 0.056 | R38: =Q38 -> 0.056 | ... AC38: =AB38 -> 0.056
B39: Net increase in milk production in the year ('000 Tonnes) | E39: =E38*1000 -> 8 | F39: =F38*1000 -> 16 | G39: =G38*1000 -> 24 | H39: =H38*1000 -> 32 | I39: =I38*1000 -> 40 | J39: =J38*1000 -> 56 | K39: =K38*1000 -> 56 | L39: =L38*1000 -> 56 | ... S39: =S38*1000 -> 56 | T39: =S39 -> 56 | U39: =T39 -> 56 | V39: =U39 -> 56 | W39: =V39 -> 56 | X39: =W39 -> 56 | Y39: =X39 -> 56 | Z39: =Y39 -> 56 | AA39: =Z39 -> 56 | ... AC39: =AB39 -> 56
B41: Weighted average milk yield, Kg/day | C41: =+C59*1.03 -> 4.6587415
B42: Milk Productivity with RBP Intervention (Kg/day/animal), Incremental | C42: =+C41*E59 -> 0.46587415
B43: Milk Poduction with RBP intervention (Million tonnes), Incremental | C43: Million Tonnes | E43: 0 | F43: =$C$42*E6*365/1000000000 -> 0.062236128 | G43: =$C$42*F6*365/1000000000 -> 0.12600265 | H43: =$C$42*G6*365/1000000000 -> 0.20201235 | I43: =$C$42*H6*365/1000000000 -> 0.30914011 | J43: =$C$42*I6*365/1000000000 -> 0.40688144 | K43: =$C$42*J6*365/1000000000 -> 0.46238382 | L43: =$C$42*K6*365/1000000000 -> 0.46238382 | M43: =$C$42*L6*365/1000000000 -> 0.46238382 | ... AC43: =$C$42*AB6*365/1000000000 -> 0.46238382
B44: Quantity of Additional Fat Produced with RBP (Million tonnes) | C44: ='Feed and Fodder'!S4 -> 0.0025 | E44: =$C$44*E43 -> 0 | F44: =$C$44*F43 -> 0.00015559032 | G44: =$C$44*G43 -> 0.00031500663 | H44: =$C$44*H43 -> 0.00050503087 | I44: =$C$44*I43 -> 0.00077285027 | J44: =$C$44*J43 -> 0.0010172036 | K44: =$C$44*K43 -> 0.0011559596 | L44: =$C$44*L43 -> 0.0011559596 | ... AC44: =$C$44*AC43 -> 0.0011559596
B45: Reduction in Feeding Cost | C45: Million Rupees | E45: 0 | F45: =+$C$71*$C$41*E6*365/1000000 -> 359.69482 | G45: =+$C$71*$C$41*F6*365/1000000 -> 728.23459 | H45: =+$C$71*$C$41*G6*365/1000000 -> 1167.534 | I45: =+$C$71*$C$41*H6*365/1000000 -> 1786.6808 | J45: =+$C$71*$C$41*I6*365/1000000 -> 2351.5786 | K45: =+$C$71*$C$41*J6*365/1000000 -> 2672.3556 | L45: =+$C$71*$C$41*K6*365/1000000 -> 2672.3556 | M45: =+$C$71*$C$41*L6*365/1000000 -> 2672.3556 | ... AC45: =+$C$71*$C$41*AB6*365/1000000 -> 2672.3556
B47: Reduction in Methane Emissions (CER units per annum) | C47: ='Feed and Fodder'!D33 -> 0.16453421 | E47: 0 | F47: =$C$47*E6 -> 60219.522 | G47: =$C$47*F6 -> 121919.85 | H47: =$C$47*G6 -> 195466.64 | I47: =$C$47*H6 -> 299123.2 | J47: =$C$47*I6 -> 393697.46 | K47: =$C$47*J6 -> 447401.43 | L47: =$C$47*K6 -> 447401.43 | M47: =$C$47*L6 -> 447401.43 | ... AC47: =$C$47*AB6 -> 447401.43
B48: Benefit due to reduction in Methane Emissions ( Rs million per annum) | C48: ='Feed and Fodder'!C34 -> 740 | E48: =E47*$C$48/1000000 -> 0 | F48: =F47*$C$48/1000000 -> 44.562446 | G48: =G47*$C$48/1000000 -> 90.22069 | H48: =H47*$C$48/1000000 -> 144.64532 | I48: =I47*$C$48/1000000 -> 221.35117 | J48: =J47*$C$48/1000000 -> 291.33612 | K48: =K47*$C$48/1000000 -> 331.07706 | L48: =L47*$C$48/1000000 -> 331.07706 | ... AC48: =AC47*$C$48/1000000 -> 331.07706
B50: Benefit due to increase in milk productivity (Rs Million pe annum) | E50: =+E43*$G$62 -> 0 | F50: =+F43*$G$62 -> 190.70142 | G50: =+G43*$G$62 -> 386.09222 | H50: =+H43*$G$62 -> 618.99806 | I50: =+I43*$G$62 -> 947.25461 | J50: =+J43*$G$62 -> 1246.7496 | K50: =+K43*$G$62 -> 1416.8178 | L50: =+L43*$G$62 -> 1416.8178 | ... AC50: =+AC43*$G$62 -> 1416.8178
B52: Total Benefits from RBP Programme | E52: =+SUM(E45,E48,E50) -> 0 | F52: =+SUM(F45,F48,F50) -> 594.95869 | G52: =+SUM(G45,G48,G50) -> 1204.5475 | H52: =+SUM(H45,H48,H50) -> 1931.1774 | I52: =+SUM(I45,I48,I50) -> 2955.2866 | J52: =+SUM(J45,J48,J50) -> 3889.6643 | K52: =+SUM(K45,K48,K50) -> 4420.2504 | L52: =+SUM(L45,L48,L50) -> 4420.2504 | ... AC52: =+SUM(AC45,AC48,AC50) -> 4420.2504
B55: Assumptions :
J56: =+C57*C42 -> 170.04406
B57: Number of days in lactation considered | C57: 365 | G57: Incremental | J57: =+J56*1.03 -> 175.14539 | K57: =+J57/1000 -> 0.17514539
G58: Lactn Yield, L | J58: =+J57*J6 -> 4.7625534e+08 | K58: =+K57*2.94 -> 0.51492744
B59: Average Mik yield ( l/day) | C59: =+SUMPRODUCT(C61:C63,E61:E63) -> 4.52305 | E59: ='Feed and Fodder (F) Zone.1'!$E$59 -> 0.1 | G59: =+C59*C57*E59 -> 165.09132
C60: l/day | E60: Proportion Considered
B61: Indigenous cows | C61: 2.136 | E61: 0.35 | G61: Financial Gross Margin | I61: Rs/MT
B62: Cross Breds | C62: 6.869 | E62: 0.35 | G62: 3064.1595
B63: buffaloes | C63: 4.571 | E63: ='Feed and Fodder'!C25 -> 0.3
G65: Financial Production Cost | I65: Rs/Kg
B66: Unit Prodn Cost, Rs/Kg | C66: =+G66 -> 16.512908 | G66: 16.512908
B67: Feed and Fodder Cost, % | C67: 0.7
B68: Feed and Fodder Cost, Rs/Kg | C68: =+C66*C67 -> 11.559036
B70: Reduction in Feed and Fodder Cost, % | C70: 0.05
B71: Savings in Feed and Fodder Cost, Rs/Kg | C71: =+C68*C70 -> 0.57795179
C75: 1 | E75: Yr-1 | F75: Yr-2 | G75: Yr-3 | H75: Yr-4 | I75: Yr-5 | J75: Yr-6 | K75: Yr-7 | L75: Yr-8 | M75: Yr-9 | N75: Yr-10 | O75: Yr-11 | P75: Yr-12 | Q75: Yr-13 | R75: Yr-14 | S75: Yr-15 | T75: Yr-16 | U75: Yr-17 | V75: Yr-18 | W75: Yr-19 | X75: Yr-20 | Y75: Yr-21 | Z75: Yr-22 | AA75: Yr-23 | AB75: Yr-24 | AC75: Yr-25 | AD75: Yr-26
B76: For EFA Analysis | C76: Adopters | E76: 0 | F76: 0 | G76: 0.25 | H76: 0.5 | I76: 0.75 | J76: 1 | K76: 1 | L76: 1 | M76: 1 | N76: 1 | O76: 1 | P76: 1 | Q76: 1 | R76: 1 | S76: 1 | T76: 1 | U76: 1 | V76: 1 | W76: 1 | X76: 1 | Y76: 1 | Z76: 1 | AA76: 1 | AB76: 1 | AC76: 1 | AD76: 1
C77: 0.05 | E77: =+$C77*E76*$C$75 -> 0 | F77: =+$C77*F76*$C$75 -> 0 | G77: =+$C77*G76*$C$75 -> 0.0125 | H77: =+$C77*H76*$C$75 -> 0.025 | I77: =+$C77*I76*$C$75 -> 0.0375 | J77: =+$C77*J76*$C$75 -> 0.05 | K77: =+$C77*K76*$C$75 -> 0.05 | L77: =+$C77*L76*$C$75 -> 0.05 | ... AD77: =+$C77*AD76*$C$75 -> 0.05
C78: 0.1 | F78: =+$C78*E76*$C$75 -> 0 | G78: =+$C78*F76*$C$75 -> 0 | H78: =+$C78*G76*$C$75 -> 0.025 | I78: =+$C78*H76*$C$75 -> 0.05 | J78: =+$C78*I76*$C$75 -> 0.075 | K78: =+$C78*J76*$C$75 -> 0.1 | L78: =+$C78*K76*$C$75 -> 0.1 | M78: =+$C78*L76*$C$75 -> 0.1 | ... AD78: =+$C78*AC76*$C$75 -> 0.1
C79: 0.2 | G79: =+$C79*E76*$C$75 -> 0 | H79: =+$C79*F76*$C$75 -> 0 | I79: =+$C79*G76*$C$75 -> 0.05 | J79: =+$C79*H76*$C$75 -> 0.1 | K79: =+$C79*I76*$C$75 -> 0.15 | L79: =+$C79*J76*$C$75 -> 0.2 | M79: =+$C79*K76*$C$75 -> 0.2 | N79: =+$C79*L76*$C$75 -> 0.2 | ... AD79: =+$C79*AB76*$C$75 -> 0.2
C80: 0.25 | H80: =+$C80*E76*$C$75 -> 0 | I80: =+$C80*F76*$C$75 -> 0 | J80: =+$C80*G76*$C$75 -> 0.0625 | K80: =+$C80*H76*$C$75 -> 0.125 | L80: =+$C80*I76*$C$75 -> 0.1875 | M80: =+$C80*J76*$C$75 -> 0.25 | N80: =+$C80*K76*$C$75 -> 0.25 | O80: =+$C80*L76*$C$75 -> 0.25 | ... AD80: =+$C80*AA76*$C$75 -> 0.25
C81: 0.3 | I81: =+$C81*E76*$C$75 -> 0 | J81: =+$C81*F76*$C$75 -> 0 | K81: =+$C81*G76*$C$75 -> 0.075 | L81: =+$C81*H76*$C$75 -> 0.15 | M81: =+$C81*I76*$C$75 -> 0.225 | N81: =+$C81*J76*$C$75 -> 0.3 | O81: =+$C81*K76*$C$75 -> 0.3 | P81: =+$C81*L76*$C$75 -> 0.3 | ... AD81: =+$C81*Z76*$C$75 -> 0.3
C82: 0.1 | J82: =+$C82*E76*$C$75 -> 0 | K82: =+$C82*F76*$C$75 -> 0 | L82: =+$C82*G76*$C$75 -> 0.025 | M82: =+$C82*H76*$C$75 -> 0.05 | N82: =+$C82*I76*$C$75 -> 0.075 | O82: =+$C82*J76*$C$75 -> 0.1 | P82: =+$C82*K76*$C$75 -> 0.1 | Q82: =+$C82*L76*$C$75 -> 0.1 | ... AD82: =+$C82*Y76*$C$75 -> 0.1
C83: =+SUM(C77:C82) -> 1 | E83: =SUM(E77:E82) -> 0 | F83: =SUM(F77:F82) -> 0 | G83: =SUM(G77:G82) -> 0.0125 | H83: =SUM(H77:H82) -> 0.05 | I83: =SUM(I77:I82) -> 0.1375 | J83: =SUM(J77:J82) -> 0.2875 | K83: =SUM(K77:K82) -> 0.5 | L83: =SUM(L77:L82) -> 0.7125 | ... AD83: =SUM(AD77:AD82) -> 1
B84: Zone-2
C85: 0.5
B86: =+B45 -> Reduction in Feeding Cost | E86: =+E$83*E45*$C$85 -> 0 | F86: =+F$83*F45*$C$85 -> 0 | G86: =+G$83*G45*$C$85 -> 4.5514662 | H86: =+H$83*H45*$C$85 -> 29.18835 | I86: =+I$83*I45*$C$85 -> 122.83431 | J86: =+J$83*J45*$C$85 -> 338.03942 | K86: =+K$83*K45*$C$85 -> 668.0889 | L86: =+L$83*L45*$C$85 -> 952.02668 | ... AD86: =+AD$83*AD45*$C$85 -> 0 | AF86: =+AC86/SUM($AC$86:$AC$90) -> 0.60457108
B88: =+B48 -> Benefit due to reduction in Methane Emissions ( Rs million per annum) | E88: =+E$83*E48*$C$85 -> 0 | F88: =+F$83*F48*$C$85 -> 0 | G88: =+G$83*G48*$C$85 -> 0.56387931 | H88: =+H$83*H48*$C$85 -> 3.6161329 | I88: =+I$83*I48*$C$85 -> 15.217893 | J88: =+J$83*J48*$C$85 -> 41.879568 | K88: =+K$83*K48*$C$85 -> 82.769265 | L88: =+L$83*L48*$C$85 -> 117.9462 | ... AD88: =+AD$83*AD48*$C$85 -> 0 | AF88: =+AC88/SUM($AC$86:$AC$90) -> 0.074900068
B90: =+B50 -> Benefit due to increase in milk productivity (Rs Million pe annum) | E90: =+E$83*E50*$C$85 -> 0 | F90: =+F$83*F50*$C$85 -> 0 | G90: =+G$83*G50*$C$85 -> 2.4130764 | H90: =+H$83*H50*$C$85 -> 15.474951 | I90: =+I$83*I50*$C$85 -> 65.123754 | J90: =+J$83*J50*$C$85 -> 179.22026 | K90: =+K$83*K50*$C$85 -> 354.20445 | L90: =+L$83*L50*$C$85 -> 504.74133 | ... AD90: =+AD$83*AD50*$C$85 -> 0 | AF90: =+AC90/SUM($AC$86:$AC$90) -> 0.32052885
AC92: =+SUM(AC86:AC90) -> 2210.1252

Sheet Feed and Fodder (E) Zone.1
A1: Contribution of Feed & Nutrition to Additional Milk Production
C2: Current | E2: 2011-12 | F2: 2012-13 | G2: 2013-14 | H2: 2014-15 | I2: 2015-16 | J2: 2016-17 | K2: 2017-18 | L2: 2018-19 | M2: 2019-20 | N2: 2020-21 | O2: 2021-22 | P2: 2022-23 | Q2: 2023-24 | R2: 2024-25 | S2: 2025-26 | T2: 2026-27 | U2: 2027-28 | V2: 2028-29 | W2: 2029-30 | X2: 2030-31 | Y2: 2031-32 | Z2: 2032-33 | AA2: 2033-34 | AB2: 2034-35 | AC2: 2036-37
A3: A. | B3: Ration Balancing Programme RBP
B4: PDAs (Nos.) | C4: 25 | E4: 830 | F4: 1270 | G4: 730 | H4: 730 | I4: 1630 | J4: 2010 | K4: =J4 -> 2010 | L4: =K4 -> 2010 | M4: =L4 -> 2010 | N4: =M4 -> 2010 | O4: =N4 -> 2010 | P4: =O4 -> 2010 | Q4: =P4 -> 2010 | R4: =Q4 -> 2010 | S4: =R4 -> 2010
B5: Villages (Nos) | E5: 5500 | F5: 11100 | G5: 17700 | H5: 27300 | I5: 35880 | J5: 40320 | K5: 40320 | L5: 40320 | M5: 40320 | N5: 40320 | O5: 40320 | P5: 40320 | Q5: 40320 | R5: 40320 | S5: 40320 | T5: 40320 | U5: 40320 | V5: 40320 | W5: 40320 | X5: 40320 | Y5: 40320 | Z5: 40320 | AA5: 40320 | AB5: 40320 | AC5: 40320
B6: Animals covered (Nos) | E6: 366000 | F6: 741000 | G6: 1188000 | H6: 1818000 | I6: 2392800 | J6: 2719200 | K6: 2719200 | L6: 2719200 | M6: 2719200 | N6: 2719200 | O6: 2719200 | P6: 2719200 | Q6: 2719200 | R6: 2719200 | S6: 2719200 | T6: 2719200 | U6: 2719200 | V6: 2719200 | W6: 2719200 | X6: 2719200 | Y6: 2719200 | Z6: 2719200 | AA6: 2719200 | AB6: 2719200 | AC6: 2719200
B7: Average increase in milk production due to the programme (KgPD/Animal) | E7: ='Feed and Fodder'!S14 -> 0.5 | F7: =E7 -> 0.5 | G7: =F7 -> 0.5 | H7: =G7 -> 0.5 | I7: =H7 -> 0.5 | J7: =I7 -> 0.5 | K7: =J7 -> 0.5 | L7: =K7 -> 0.5 | M7: =L7 -> 0.5 | ... AC7: =AB7 -> 0.5
B8: Net increase in milk production in the year (million MT*) | E8: =E6*E7*365/1000000000 -> 0.066795 | F8: =F6*F7*365/1000000000 -> 0.1352325 | G8: =G6*G7*365/1000000000 -> 0.21681 | H8: =H6*H7*365/1000000000 -> 0.331785 | I8: =I6*I7*365/1000000000 -> 0.436686 | J8: =J6*J7*365/1000000000 -> 0.496254 | K8: =K6*K7*365/1000000000 -> 0.496254 | L8: =L6*L7*365/1000000000 -> 0.496254 | ... AC8: =AC6*AC7*365/1000000000 -> 0.496254
A10: B | B10: Fodder Seed
B11: Fodder Seed Plants (Nos) | E11: 1 | F11: 2 | G11: 4 | H11: 5 | I11: 6 | J11: 7 | K11: =J11 -> 7 | L11: =K11 -> 7 | M11: =L11 -> 7 | N11: =M11 -> 7 | O11: =N11 -> 7 | P11: =O11 -> 7 | Q11: =P11 -> 7 | R11: =Q11 -> 7 | ... AC11: =AB11 -> 7
B12: Capacity of Fodder Seed Plants (MTD) | E12: 10 | F12: 10 | G12: 10 | H12: 10 | I12: 10 | J12: 10 | K12: 10 | L12: 10 | M12: 10 | N12: 10 | O12: 10 | P12: 10 | Q12: 10 | R12: 10 | S12: 10 | T12: =S12 -> 10 | U12: =T12 -> 10 | V12: =U12 -> 10 | W12: =V12 -> 10 | X12: =W12 -> 10 | Y12: =X12 -> 10 | Z12: =Y12 -> 10 | AA12: =Z12 -> 10 | ... AC12: =AB12 -> 10
B13: Anticipated annual Fodder Seed Production (MT) | E13: 300 | F13: 600 | G13: 1200 | H13: 1500 | I13: 1800 | J13: 2100 | K13: =J13 -> 2100 | L13: =K13 -> 2100 | M13: =L13 -> 2100 | N13: =M13 -> 2100 | O13: =N13 -> 2100 | P13: =O13 -> 2100 | Q13: =P13 -> 2100 | R13: =Q13 -> 2100 | ... AC13: =AB13 -> 2100
B14: Fodder seed required per hactare (Kg) | E14: 50 | F14: 50 | G14: 50 | H14: 50 | I14: 50 | J14: 50 | K14: 50 | L14: 50 | M14: 50 | N14: 50 | O14: 50 | P14: 50 | Q14: 50 | R14: 50 | S14: 50 | T14: =S14 -> 50 | U14: =T14 -> 50 | V14: =U14 -> 50 | W14: =V14 -> 50 | X14: =W14 -> 50 | Y14: =X14 -> 50 | Z14: =Y14 -> 50 | AA14: =Z14 -> 50 | ... AC14: =AB14 -> 50
B15: Total area under fodder seed production (ha) | E15: =E13*1000/E14 -> 6000 | F15: =F13*1000/F14 -> 12000 | G15: =G13*1000/G14 -> 24000 | H15: =H13*1000/H14 -> 30000 | I15: =I13*1000/I14 -> 36000 | J15: =J13*1000/J14 -> 42000 | K15: =K13*1000/K14 -> 42000 | L15: =L13*1000/L14 -> 42000 | ... S15: =S13*1000/S14 -> 42000 | T15: =S15 -> 42000 | U15: =T15 -> 42000 | V15: =U15 -> 42000 | W15: =V15 -> 42000 | X15: =W15 -> 42000 | Y15: =X15 -> 42000 | Z15: =Y15 -> 42000 | AA15: =Z15 -> 42000 | ... AC15: =AB15 -> 42000
B16: Increase in fodder production per hactare (MT) | E16: 40 | F16: 40 | G16: 40 | H16: 40 | I16: 40 | J16: 40 | K16: 40 | L16: 40 | M16: 40 | N16: 40 | O16: 40 | P16: 40 | Q16: 40 | R16: 40 | S16: 40 | T16: =S16 -> 40 | U16: =T16 -> 40 | V16: =U16 -> 40 | W16: =V16 -> 40 | X16: =W16 -> 40 | Y16: =X16 -> 40 | Z16: =Y16 -> 40 | AA16: =Z16 -> 40 | ... AC16: =AB16 -> 40
B17: Annual increase in fodder production (million MT) | E17: =E15*E16/1000000 -> 0.24 | F17: =F15*F16/1000000 -> 0.48 | G17: =G15*G16/1000000 -> 0.96 | H17: =H15*H16/1000000 -> 1.2 | I17: =I15*I16/1000000 -> 1.44 | J17: =J15*J16/1000000 -> 1.68 | K17: =K15*K16/1000000 -> 1.68 | L17: =L15*L16/1000000 -> 1.68 | ... S17: =S15*S16/1000000 -> 1.68 | T17: =S17 -> 1.68 | U17: =T17 -> 1.68 | V17: =U17 -> 1.68 | W17: =V17 -> 1.68 | X17: =W17 -> 1.68 | Y17: =X17 -> 1.68 | Z17: =Y17 -> 1.68 | AA17: =Z17 -> 1.68 | ... AC17: =AB17 -> 1.68
B18: Increase in milk production for every 10 Kg fodder (Kg) | E18: 1 | F18: 1 | G18: 1 | H18: 1 | I18: 1 | J18: 1 | K18: 1 | L18: 1 | M18: 1 | N18: 1 | O18: 1 | P18: 1 | Q18: 1 | R18: 1 | S18: 1 | T18: =S18 -> 1 | U18: =T18 -> 1 | V18: =U18 -> 1 | W18: =V18 -> 1 | X18: =W18 -> 1 | Y18: =X18 -> 1 | Z18: =Y18 -> 1 | AA18: =Z18 -> 1 | ... AC18: =AB18 -> 1
B19: Net increase in milk production in the year (million MT) | E19: =E17*E18/10 -> 0.024 | F19: =F17*F18/10 -> 0.048 | G19: =G17*G18/10 -> 0.096 | H19: =H17*H18/10 -> 0.12 | I19: =I17*I18/10 -> 0.144 | J19: =J17*J18/10 -> 0.168 | K19: =K17*K18/10 -> 0.168 | L19: =L17*L18/10 -> 0.168 | ... S19: =S17*S18/10 -> 0.168 | T19: =S19 -> 0.168 | U19: =T19 -> 0.168 | V19: =U19 -> 0.168 | W19: =V19 -> 0.168 | X19: =W19 -> 0.168 | Y19: =X19 -> 0.168 | Z19: =Y19 -> 0.168 | AA19: =Z19 -> 0.168 | ... AC19: =AB19 -> 0.168
B20: Net increase in milk production in the year ('000 Tonnes) | E20: =E19*1000 -> 24 | F20: =F19*1000 -> 48 | G20: =G19*1000 -> 96 | H20: =H19*1000 -> 120 | I20: =I19*1000 -> 144 | J20: =J19*1000 -> 168 | K20: =K19*1000 -> 168 | L20: =L19*1000 -> 168 | ... S20: =S19*1000 -> 168 | T20: =S20 -> 168 | U20: =T20 -> 168 | V20: =U20 -> 168 | W20: =V20 -> 168 | X20: =W20 -> 168 | Y20: =X20 -> 168 | Z20: =Y20 -> 168 | AA20: =Z20 -> 168 | ... AC20: =AB20 -> 168
A22: C | B22: Straw Densification Plants ( Nos.) | E22: 0 | F22: 1 | G22: 1 | H22: 2 | I22: 2 | J22: 2 | K22: =J22 -> 2 | L22: =K22 -> 2 | M22: =L22 -> 2 | N22: =M22 -> 2 | O22: =N22 -> 2 | P22: =O22 -> 2 | Q22: =P22 -> 2 | R22: =Q22 -> 2 | ... AC22: =AB22 -> 2
B23: Capacity of Straw Densification Plants (MTD) | E23: 40 | F23: 40 | G23: 40 | H23: 40 | I23: 40 | J23: 40 | K23: 40 | L23: 40 | M23: 40 | N23: 40 | O23: 40 | P23: 40 | Q23: 40 | R23: 40 | S23: 40 | T23: 40 | U23: 40 | V23: 40 | W23: 40 | X23: 40 | Y23: 40 | Z23: 40 | AA23: 40 | AB23: 40 | AC23: 40
B24: Anticipated Annual Production (MT) | E24: =E22*E23*300 -> 0 | F24: =F22*F23*300 -> 12000 | G24: =G22*G23*300 -> 12000 | H24: =H22*H23*300 -> 24000 | I24: =I22*I23*300 -> 24000 | J24: =J22*J23*300 -> 24000 | K24: =K22*K23*300 -> 24000 | L24: =L22*L23*300 -> 24000 | ... AC24: =AC22*AC23*300 -> 24000
A25: C | B25: Devt of permanent pasture & common grazing lands
B26: Live Fencing, Plantation, Perennial Grass Seeding, Land and Irrigation Development (Area to be covered) | E26: 400 | F26: 800 | G26: 1200 | H26: 1600 | I26: 2000 | J26: 2800 | K26: =J26 -> 2800 | L26: =K26 -> 2800 | M26: =L26 -> 2800 | N26: =M26 -> 2800 | O26: =N26 -> 2800 | P26: =O26 -> 2800 | Q26: =P26 -> 2800 | R26: =Q26 -> 2800 | ... AC26: =AB26 -> 2800
B27: Incremental Biomass (From 0.75 MT/ hect/yr to 5.75 MT/hect/yr) | E27: =E26*5 -> 2000 | F27: =F26*5 -> 4000 | G27: =G26*5 -> 6000 | H27: =H26*5 -> 8000 | I27: =I26*5 -> 10000 | J27: =J26*5 -> 14000 | K27: =J27 -> 14000 | L27: =K27 -> 14000 | M27: =L27 -> 14000 | N27: =M27 -> 14000 | O27: =N27 -> 14000 | P27: =O27 -> 14000 | Q27: =P27 -> 14000 | R27: =Q27 -> 14000 | ... AC27: =AB27 -> 14000
B28: Annual increase in fodder production (million MT) | E28: =E27/1000000 -> 0.002 | F28: =F27/1000000 -> 0.004 | G28: =G27/1000000 -> 0.006 | H28: =H27/1000000 -> 0.008 | I28: =I27/1000000 -> 0.01 | J28: =J27/1000000 -> 0.014 | K28: =J28 -> 0.014 | L28: =K28 -> 0.014 | M28: =L28 -> 0.014 | N28: =M28 -> 0.014 | O28: =N28 -> 0.014 | P28: =O28 -> 0.014 | Q28: =P28 -> 0.014 | R28: =Q28 -> 0.014 | ... AC28: =AB28 -> 0.014
B29: Increase in milk production for every 10 Kg fodder (Kg) | E29: 1 | F29: 1 | G29: 1 | H29: 1 | I29: 1 | J29: 1 | K29: =J29 -> 1 | L29: =K29 -> 1 | M29: =L29 -> 1 | N29: =M29 -> 1 | O29: =N29 -> 1 | P29: =O29 -> 1 | Q29: =P29 -> 1 | R29: =Q29 -> 1 | ... AC29: =AB29 -> 1
B30: Net increase in milk production in the year (million MT) | E30: =E28*E29/10 -> 0.0002 | F30: =F28*F29/10 -> 0.0004 | G30: =G28*G29/10 -> 0.0006 | H30: =H28*H29/10 -> 0.0008 | I30: =I28*I29/10 -> 0.001 | J30: =J28*J29/10 -> 0.0014 | K30: =J30 -> 0.0014 | L30: =K30 -> 0.0014 | M30: =L30 -> 0.0014 | N30: =M30 -> 0.0014 | O30: =N30 -> 0.0014 | P30: =O30 -> 0.0014 | Q30: =P30 -> 0.0014 | R30: =Q30 -> 0.0014 | ... AC30: =AB30 -> 0.0014
B31: Net increase in milk production in the year ('000 Tonnes) | E31: =E30*1000 -> 0.2 | F31: =F30*1000 -> 0.4 | G31: =G30*1000 -> 0.6 | H31: =H30*1000 -> 0.8 | I31: =I30*1000 -> 1 | J31: =J30*1000 -> 1.4 | K31: =K30*1000 -> 1.4 | L31: =L30*1000 -> 1.4 | ... S31: =S30*1000 -> 1.4 | T31: =S31 -> 1.4 | U31: =T31 -> 1.4 | V31: =U31 -> 1.4 | W31: =V31 -> 1.4 | X31: =W31 -> 1.4 | Y31: =X31 -> 1.4 | Z31: =Y31 -> 1.4 | AA31: =Z31 -> 1.4 | ... AC31: =AB31 -> 1.4
A32: D | B32: Organising Varietal Demonstrations (1/10 of Hect) | E32: 20000 | F32: 40000 | G32: 60000 | H32: 80000 | I32: 100000 | J32: 140000 | K32: =J32 -> 140000 | L32: =K32 -> 140000 | M32: =L32 -> 140000 | N32: =M32 -> 140000 | O32: =N32 -> 140000 | P32: =O32 -> 140000 | Q32: =P32 -> 140000 | R32: =Q32 -> 140000 | ... AC32: =AB32 -> 140000
B33: Villages covered under Varietal Demonstrations (nos.) | E33: =E32/4 -> 5000 | F33: =F32/4 -> 10000 | G33: =G32/4 -> 15000 | H33: =H32/4 -> 20000 | I33: =I32/4 -> 25000 | J33: =J32/4 -> 35000 | K33: =J33 -> 35000 | L33: =K33 -> 35000 | M33: =L33 -> 35000 | N33: =M33 -> 35000 | O33: =N33 -> 35000 | P33: =O33 -> 35000 | Q33: =P33 -> 35000 | R33: =Q33 -> 35000 | ... AC33: =AB33 -> 35000
B34: Villages covered under Varietal Demonstrations (nos.) | E34: =E32/10 -> 2000 | F34: =F32/10 -> 4000 | G34: =G32/10 -> 6000 | H34: =H32/10 -> 8000 | I34: =I32/10 -> 10000 | J34: =J32/10 -> 14000 | K34: =J34 -> 14000 | L34: =K34 -> 14000 | M34: =L34 -> 14000 | N34: =M34 -> 14000 | O34: =N34 -> 14000 | P34: =O34 -> 14000 | Q34: =P34 -> 14000 | R34: =Q34 -> 14000 | ... AC34: =AB34 -> 14000
B35: Increase in fodder production per hactare (MT) | E35: 40 | F35: 40 | G35: 40 | H35: 40 | I35: 40 | J35: 40 | K35: 40 | L35: =K35 -> 40 | M35: =L35 -> 40 | N35: =M35 -> 40 | O35: =N35 -> 40 | P35: =O35 -> 40 | Q35: =P35 -> 40 | R35: =Q35 -> 40 | S35: =R35 -> 40 | ... AC35: =AB35 -> 40
B36: Annual increase in fodder production (million MT) | E36: =E34*E35/1000000 -> 0.08 | F36: =F34*F35/1000000 -> 0.16 | G36: =G34*G35/1000000 -> 0.24 | H36: =H34*H35/1000000 -> 0.32 | I36: =I34*I35/1000000 -> 0.4 | J36: =J34*J35/1000000 -> 0.56 | K36: =K34*K35/1000000 -> 0.56 | L36: =K36 -> 0.56 | M36: =L36 -> 0.56 | N36: =M36 -> 0.56 | O36: =N36 -> 0.56 | P36: =O36 -> 0.56 | Q36: =P36 -> 0.56 | R36: =Q36 -> 0.56 | S36: =R36 -> 0.56 | ... AC36: =AB36 -> 0.56
B37: Increase in milk production for every 10 Kg fodder (Kg) | E37: 1 | F37: 1 | G37: 1 | H37: 1 | I37: 1 | J37: 1 | K37: =J37 -> 1 | L37: =K37 -> 1 | M37: =L37 -> 1 | N37: =M37 -> 1 | O37: =N37 -> 1 | P37: =O37 -> 1 | Q37: =P37 -> 1 | R37: =Q37 -> 1 | ... AC37: =AB37 -> 1
B38: Net increase in milk production in the year (million MT) | E38: =E36*E37/10 -> 0.008 | F38: =F36*F37/10 -> 0.016 | G38: =G36*G37/10 -> 0.024 | H38: =H36*H37/10 -> 0.032 | I38: =I36*I37/10 -> 0.04 | J38: =J36*J37/10 -> 0.056 | K38: =J38 -> 0.056 | L38: =K38 -> 0.056 | M38: =L38 -> 0.056 | N38: =M38 -> 0.056 | O38: =N38 -> 0.056 | P38: =O38 -> 0.056 | Q38: =P38 -> 0.056 | R38: =Q38 -> 0.056 | ... AC38: =AB38 -> 0.056
B39: Net increase in milk production in the year ('000 Tonnes) | E39: =E38*1000 -> 8 | F39: =F38*1000 -> 16 | G39: =G38*1000 -> 24 | H39: =H38*1000 -> 32 | I39: =I38*1000 -> 40 | J39: =J38*1000 -> 56 | K39: =K38*1000 -> 56 | L39: =L38*1000 -> 56 | ... S39: =S38*1000 -> 56 | T39: =S39 -> 56 | U39: =T39 -> 56 | V39: =U39 -> 56 | W39: =V39 -> 56 | X39: =W39 -> 56 | Y39: =X39 -> 56 | Z39: =Y39 -> 56 | AA39: =Z39 -> 56 | ... AC39: =AB39 -> 56
E40: =+E6 -> 366000 | F40: =+F6-E6 -> 375000 | G40: =+G6-F6 -> 447000 | H40: =+H6-G6 -> 630000 | I40: =+I6-H6 -> 574800 | J40: =+J6-I6 -> 326400 | K40: =+K6-J6 -> 0 | L40: =+L6-K6 -> 0
B41: Weighted average milk yield, Kg/day | C41: =+C59*1.03 -> 4.6587415
B42: Milk Productivity with RBP Intervention (Kg/day/animal), Incremental | C42: =+C41*E59 -> 0.46587415
B43: Milk Poduction with RBP intervention (Million tonnes), Incremental | C43: Million Tonnes | E43: 0 | F43: =$C$42*E6*365/1000000000 -> 0.062236128 | G43: =$C$42*F6*365/1000000000 -> 0.12600265 | H43: =$C$42*G6*365/1000000000 -> 0.20201235 | I43: =$C$42*H6*365/1000000000 -> 0.30914011 | J43: =$C$42*I6*365/1000000000 -> 0.40688144 | K43: =$C$42*J6*365/1000000000 -> 0.46238382 | L43: =$C$42*K6*365/1000000000 -> 0.46238382 | M43: =$C$42*L6*365/1000000000 -> 0.46238382 | ... AC43: =$C$42*AB6*365/1000000000 -> 0.46238382
B44: Quantity of Additional Fat Produced with RBP (Million tonnes) | C44: ='Feed and Fodder'!S4 -> 0.0025 | E44: =$C$44*E43 -> 0 | F44: =$C$44*F43 -> 0.00015559032 | G44: =$C$44*G43 -> 0.00031500663 | H44: =$C$44*H43 -> 0.00050503087 | I44: =$C$44*I43 -> 0.00077285027 | J44: =$C$44*J43 -> 0.0010172036 | K44: =$C$44*K43 -> 0.0011559596 | L44: =$C$44*L43 -> 0.0011559596 | ... AC44: =$C$44*AC43 -> 0.0011559596
B45: Reduction in Feeding Cost | C45: Million Rupees | E45: 0 | F45: =+$C$71*$C$41*E6*365/1000000 -> 363.66121 | G45: =+$C$71*$C$41*F6*365/1000000 -> 736.26491 | H45: =+$C$71*$C$41*G6*365/1000000 -> 1180.4085 | I45: =+$C$71*$C$41*H6*365/1000000 -> 1806.3827 | J45: =+$C$71*$C$41*I6*365/1000000 -> 2377.5097 | K45: =+$C$71*$C$41*J6*365/1000000 -> 2701.824 | L45: =+$C$71*$C$41*K6*365/1000000 -> 2701.824 | M45: =+$C$71*$C$41*L6*365/1000000 -> 2701.824 | ... AC45: =+$C$71*$C$41*AB6*365/1000000 -> 2701.824
B47: Reduction in Methane Emissions (CER units per annum) | C47: ='Feed and Fodder'!D33 -> 0.16453421 | E47: 0 | F47: =$C$47*E6 -> 60219.522 | G47: =$C$47*F6 -> 121919.85 | H47: =$C$47*G6 -> 195466.64 | I47: =$C$47*H6 -> 299123.2 | J47: =$C$47*I6 -> 393697.46 | K47: =$C$47*J6 -> 447401.43 | L47: =$C$47*K6 -> 447401.43 | M47: =$C$47*L6 -> 447401.43 | ... AC47: =$C$47*AB6 -> 447401.43
B48: Benefit due to reduction in Methane Emissions ( Rs million per annum) | C48: ='Feed and Fodder'!C34 -> 740 | E48: =E47*$C$48/1000000 -> 0 | F48: =F47*$C$48/1000000 -> 44.562446 | G48: =G47*$C$48/1000000 -> 90.22069 | H48: =H47*$C$48/1000000 -> 144.64532 | I48: =I47*$C$48/1000000 -> 221.35117 | J48: =J47*$C$48/1000000 -> 291.33612 | K48: =K47*$C$48/1000000 -> 331.07706 | L48: =L47*$C$48/1000000 -> 331.07706 | ... AC48: =AC47*$C$48/1000000 -> 331.07706
B50: Benefit due to increase in milk productivity (Rs Million pe annum) | E50: =+E43*$G$62 -> 0 | F50: =+F43*$G$62 -> 224.69631 | G50: =+G43*$G$62 -> 454.91793 | H50: =+H43*$G$62 -> 729.34211 | I50: =+I43*$G$62 -> 1116.1144 | J50: =+J43*$G$62 -> 1468.9982 | K50: =+K43*$G$62 -> 1669.3831 | L50: =+L43*$G$62 -> 1669.3831 | ... AC50: =+AC43*$G$62 -> 1669.3831
B52: Total Benefits from RBP Programme | E52: =+SUM(E45,E48,E50) -> 0 | F52: =+SUM(F45,F48,F50) -> 632.91996 | G52: =+SUM(G45,G48,G50) -> 1281.4035 | H52: =+SUM(H45,H48,H50) -> 2054.396 | I52: =+SUM(I45,I48,I50) -> 3143.8483 | J52: =+SUM(J45,J48,J50) -> 4137.844 | K52: =+SUM(K45,K48,K50) -> 4702.2841 | L52: =+SUM(L45,L48,L50) -> 4702.2841 | ... AC52: =+SUM(AC45,AC48,AC50) -> 4702.2841
B55: Assumptions :
J56: =+C57*C42 -> 170.04406
B57: Number of days in lactation considered | C57: 365 | G57: Incremental | J57: =+J56*1.03 -> 175.14539 | K57: =+J57/1000 -> 0.17514539
G58: Lactn Yield, L | J58: =+J57*J6 -> 4.7625534e+08 | K58: =+K57*2.94 -> 0.51492744
B59: Average Mik yield ( l/day) | C59: ='Feed and Fodder (F) Zone.2'!$C$59 -> 4.52305 | E59: ='Feed and Fodder (F) Zone.1'!$E$59 -> 0.1 | G59: =+C59*C57*E59 -> 165.09132
C60: l/day | E60: Proportion Considered
B61: Indigenous cows | C61: 2.136 | E61: 0.35 | G61: Ecomomic Gross Margin | I61: Rs/MT
B62: Cross Breds | C62: 6.869 | E62: 0.35 | G62: 3610.3838
B63: buffaloes | C63: 4.571 | E63: ='Feed and Fodder'!C25 -> 0.3
G65: Economic Production Cost | I65: Rs/Kg
B66: Unit Prodn Cost, Rs/Kg | C66: =+G66 -> 16.694998 | G66: 16.694998
B67: Feed and Fodder Cost, % | C67: 0.7
B68: Feed and Fodder Cost, Rs/Kg | C68: =+C66*C67 -> 11.686499
B70: Reduction in Feed and Fodder Cost, % | C70: 0.05
B71: Savings in Feed and Fodder Cost, Rs/Kg | C71: =+C68*C70 -> 0.58432493
C75: 1 | E75: Yr-1 | F75: Yr-2 | G75: Yr-3 | H75: Yr-4 | I75: Yr-5 | J75: Yr-6 | K75: Yr-7 | L75: Yr-8 | M75: Yr-9 | N75: Yr-10 | O75: Yr-11 | P75: Yr-12 | Q75: Yr-13 | R75: Yr-14 | S75: Yr-15 | T75: Yr-16 | U75: Yr-17 | V75: Yr-18 | W75: Yr-19 | X75: Yr-20 | Y75: Yr-21 | Z75: Yr-22 | AA75: Yr-23 | AB75: Yr-24 | AC75: Yr-25 | AD75: Yr-26
B76: For EFA Analysis | C76: Adopters | E76: 0 | F76: 0 | G76: 0.25 | H76: 0.5 | I76: 0.75 | J76: 1 | K76: 1 | L76: 1 | M76: 1 | N76: 1 | O76: 1 | P76: 1 | Q76: 1 | R76: 1 | S76: 1 | T76: 1 | U76: 1 | V76: 1 | W76: 1 | X76: 1 | Y76: 1 | Z76: 1 | AA76: 1 | AB76: 1 | AC76: 1 | AD76: 1
C77: 0.05 | E77: =+$C77*E76*$C$75 -> 0 | F77: =+$C77*F76*$C$75 -> 0 | G77: =+$C77*G76*$C$75 -> 0.0125 | H77: =+$C77*H76*$C$75 -> 0.025 | I77: =+$C77*I76*$C$75 -> 0.0375 | J77: =+$C77*J76*$C$75 -> 0.05 | K77: =+$C77*K76*$C$75 -> 0.05 | L77: =+$C77*L76*$C$75 -> 0.05 | ... AD77: =+$C77*AD76*$C$75 -> 0.05
C78: 0.1 | F78: =+$C78*E76*$C$75 -> 0 | G78: =+$C78*F76*$C$75 -> 0 | H78: =+$C78*G76*$C$75 -> 0.025 | I78: =+$C78*H76*$C$75 -> 0.05 | J78: =+$C78*I76*$C$75 -> 0.075 | K78: =+$C78*J76*$C$75 -> 0.1 | L78: =+$C78*K76*$C$75 -> 0.1 | M78: =+$C78*L76*$C$75 -> 0.1 | ... AD78: =+$C78*AC76*$C$75 -> 0.1
C79: 0.2 | G79: =+$C79*E76*$C$75 -> 0 | H79: =+$C79*F76*$C$75 -> 0 | I79: =+$C79*G76*$C$75 -> 0.05 | J79: =+$C79*H76*$C$75 -> 0.1 | K79: =+$C79*I76*$C$75 -> 0.15 | L79: =+$C79*J76*$C$75 -> 0.2 | M79: =+$C79*K76*$C$75 -> 0.2 | N79: =+$C79*L76*$C$75 -> 0.2 | ... AD79: =+$C79*AB76*$C$75 -> 0.2
C80: 0.25 | H80: =+$C80*E76*$C$75 -> 0 | I80: =+$C80*F76*$C$75 -> 0 | J80: =+$C80*G76*$C$75 -> 0.0625 | K80: =+$C80*H76*$C$75 -> 0.125 | L80: =+$C80*I76*$C$75 -> 0.1875 | M80: =+$C80*J76*$C$75 -> 0.25 | N80: =+$C80*K76*$C$75 -> 0.25 | O80: =+$C80*L76*$C$75 -> 0.25 | ... AD80: =+$C80*AA76*$C$75 -> 0.25
C81: 0.3 | I81: =+$C81*E76*$C$75 -> 0 | J81: =+$C81*F76*$C$75 -> 0 | K81: =+$C81*G76*$C$75 -> 0.075 | L81: =+$C81*H76*$C$75 -> 0.15 | M81: =+$C81*I76*$C$75 -> 0.225 | N81: =+$C81*J76*$C$75 -> 0.3 | O81: =+$C81*K76*$C$75 -> 0.3 | P81: =+$C81*L76*$C$75 -> 0.3 | ... AD81: =+$C81*Z76*$C$75 -> 0.3
C82: 0.1 | J82: =+$C82*E76*$C$75 -> 0 | K82: =+$C82*F76*$C$75 -> 0 | L82: =+$C82*G76*$C$75 -> 0.025 | M82: =+$C82*H76*$C$75 -> 0.05 | N82: =+$C82*I76*$C$75 -> 0.075 | O82: =+$C82*J76*$C$75 -> 0.1 | P82: =+$C82*K76*$C$75 -> 0.1 | Q82: =+$C82*L76*$C$75 -> 0.1 | ... AD82: =+$C82*Y76*$C$75 -> 0.1
C83: =+SUM(C77:C82) -> 1 | E83: =SUM(E77:E82) -> 0 | F83: =SUM(F77:F82) -> 0 | G83: =SUM(G77:G82) -> 0.0125 | H83: =SUM(H77:H82) -> 0.05 | I83: =SUM(I77:I82) -> 0.1375 | J83: =SUM(J77:J82) -> 0.2875 | K83: =SUM(K77:K82) -> 0.5 | L83: =SUM(L77:L82) -> 0.7125 | ... AD83: =SUM(AD77:AD82) -> 1
B84: Zone-1
C85: 0.5
B86: =+B45 -> Reduction in Feeding Cost | E86: =+E$83*E45*$C$85 -> 0 | F86: =+F$83*F45*$C$85 -> 0 | G86: =+G$83*G45*$C$85 -> 4.6016557 | H86: =+H$83*H45*$C$85 -> 29.510213 | I86: =+I$83*I45*$C$85 -> 124.18881 | J86: =+J$83*J45*$C$85 -> 341.76702 | K86: =+K$83*K45*$C$85 -> 675.45599 | L86: =+L$83*L45*$C$85 -> 962.52478 | ... AD86: =+AD$83*AD45*$C$85 -> 0 | AF86: =+AC86/SUM($AC$86:$AC$90) -> 0.57457693
B88: =+B48 -> Benefit due to reduction in Methane Emissions ( Rs million per annum) | E88: =+E$83*E48*$C$85 -> 0 | F88: =+F$83*F48*$C$85 -> 0 | G88: =+G$83*G48*$C$85 -> 0.56387931 | H88: =+H$83*H48*$C$85 -> 3.6161329 | I88: =+I$83*I48*$C$85 -> 15.217893 | J88: =+J$83*J48*$C$85 -> 41.879568 | K88: =+K$83*K48*$C$85 -> 82.769265 | L88: =+L$83*L48*$C$85 -> 117.9462 | ... AD88: =+AD$83*AD48*$C$85 -> 0 | AF88: =+AC88/SUM($AC$86:$AC$90) -> 0.070407711
B90: =+B50 -> Benefit due to increase in milk productivity (Rs Million pe annum) | E90: =+E$83*E50*$C$85 -> 0 | F90: =+F$83*F50*$C$85 -> 0 | G90: =+G$83*G50*$C$85 -> 2.8432371 | H90: =+H$83*H50*$C$85 -> 18.233553 | I90: =+I$83*I50*$C$85 -> 76.732868 | J90: =+J$83*J50*$C$85 -> 211.16848 | K90: =+K$83*K50*$C$85 -> 417.34576 | L90: =+L$83*L50*$C$85 -> 594.71771 | ... AD90: =+AD$83*AD50*$C$85 -> 0 | AF90: =+AC90/SUM($AC$86:$AC$90) -> 0.35501536

Sheet Feed and Fodder (E) Zone.2
A1: Contribution of Feed & Nutrition to Additional Milk Production
C2: Current | E2: 2011-12 | F2: 2012-13 | G2: 2013-14 | H2: 2014-15 | I2: 2015-16 | J2: 2016-17 | K2: 2017-18 | L2: 2018-19 | M2: 2019-20 | N2: 2020-21 | O2: 2021-22 | P2: 2022-23 | Q2: 2023-24 | R2: 2024-25 | S2: 2025-26 | T2: 2026-27 | U2: 2027-28 | V2: 2028-29 | W2: 2029-30 | X2: 2030-31 | Y2: 2031-32 | Z2: 2032-33 | AA2: 2033-34 | AB2: 2034-35 | AC2: 2036-37
A3: A. | B3: Ration Balancing Programme RBP
B4: PDAs (Nos.) | C4: 25 | E4: 830 | F4: 1270 | G4: 730 | H4: 730 | I4: 1630 | J4: 2010 | K4: =J4 -> 2010 | L4: =K4 -> 2010 | M4: =L4 -> 2010 | N4: =M4 -> 2010 | O4: =N4 -> 2010 | P4: =O4 -> 2010 | Q4: =P4 -> 2010 | R4: =Q4 -> 2010 | S4: =R4 -> 2010
B5: Villages (Nos) | E5: 5500 | F5: 11100 | G5: 17700 | H5: 27300 | I5: 35880 | J5: 40320 | K5: 40320 | L5: 40320 | M5: 40320 | N5: 40320 | O5: 40320 | P5: 40320 | Q5: 40320 | R5: 40320 | S5: 40320 | T5: 40320 | U5: 40320 | V5: 40320 | W5: 40320 | X5: 40320 | Y5: 40320 | Z5: 40320 | AA5: 40320 | AB5: 40320 | AC5: 40320
B6: Animals covered (Nos) | E6: 366000 | F6: 741000 | G6: 1188000 | H6: 1818000 | I6: 2392800 | J6: 2719200 | K6: 2719200 | L6: 2719200 | M6: 2719200 | N6: 2719200 | O6: 2719200 | P6: 2719200 | Q6: 2719200 | R6: 2719200 | S6: 2719200 | T6: 2719200 | U6: 2719200 | V6: 2719200 | W6: 2719200 | X6: 2719200 | Y6: 2719200 | Z6: 2719200 | AA6: 2719200 | AB6: 2719200 | AC6: 2719200
B7: Average increase in milk production due to the programme (KgPD/Animal) | E7: ='Feed and Fodder'!S14 -> 0.5 | F7: =E7 -> 0.5 | G7: =F7 -> 0.5 | H7: =G7 -> 0.5 | I7: =H7 -> 0.5 | J7: =I7 -> 0.5 | K7: =J7 -> 0.5 | L7: =K7 -> 0.5 | M7: =L7 -> 0.5 | ... AC7: =AB7 -> 0.5
B8: Net increase in milk production in the year (million MT*) | E8: =E6*E7*365/1000000000 -> 0.066795 | F8: =F6*F7*365/1000000000 -> 0.1352325 | G8: =G6*G7*365/1000000000 -> 0.21681 | H8: =H6*H7*365/1000000000 -> 0.331785 | I8: =I6*I7*365/1000000000 -> 0.436686 | J8: =J6*J7*365/1000000000 -> 0.496254 | K8: =K6*K7*365/1000000000 -> 0.496254 | L8: =L6*L7*365/1000000000 -> 0.496254 | ... AC8: =AC6*AC7*365/1000000000 -> 0.496254
A10: B | B10: Fodder Seed
B11: Fodder Seed Plants (Nos) | E11: 1 | F11: 2 | G11: 4 | H11: 5 | I11: 6 | J11: 7 | K11: =J11 -> 7 | L11: =K11 -> 7 | M11: =L11 -> 7 | N11: =M11 -> 7 | O11: =N11 -> 7 | P11: =O11 -> 7 | Q11: =P11 -> 7 | R11: =Q11 -> 7 | ... AC11: =AB11 -> 7
B12: Capacity of Fodder Seed Plants (MTD) | E12: 10 | F12: 10 | G12: 10 | H12: 10 | I12: 10 | J12: 10 | K12: 10 | L12: 10 | M12: 10 | N12: 10 | O12: 10 | P12: 10 | Q12: 10 | R12: 10 | S12: 10 | T12: =S12 -> 10 | U12: =T12 -> 10 | V12: =U12 -> 10 | W12: =V12 -> 10 | X12: =W12 -> 10 | Y12: =X12 -> 10 | Z12: =Y12 -> 10 | AA12: =Z12 -> 10 | ... AC12: =AB12 -> 10
B13: Anticipated annual Fodder Seed Production (MT) | E13: 300 | F13: 600 | G13: 1200 | H13: 1500 | I13: 1800 | J13: 2100 | K13: =J13 -> 2100 | L13: =K13 -> 2100 | M13: =L13 -> 2100 | N13: =M13 -> 2100 | O13: =N13 -> 2100 | P13: =O13 -> 2100 | Q13: =P13 -> 2100 | R13: =Q13 -> 2100 | ... AC13: =AB13 -> 2100
B14: Fodder seed required per hactare (Kg) | E14: 50 | F14: 50 | G14: 50 | H14: 50 | I14: 50 | J14: 50 | K14: 50 | L14: 50 | M14: 50 | N14: 50 | O14: 50 | P14: 50 | Q14: 50 | R14: 50 | S14: 50 | T14: =S14 -> 50 | U14: =T14 -> 50 | V14: =U14 -> 50 | W14: =V14 -> 50 | X14: =W14 -> 50 | Y14: =X14 -> 50 | Z14: =Y14 -> 50 | AA14: =Z14 -> 50 | ... AC14: =AB14 -> 50
B15: Total area under fodder seed production (ha) | E15: =E13*1000/E14 -> 6000 | F15: =F13*1000/F14 -> 12000 | G15: =G13*1000/G14 -> 24000 | H15: =H13*1000/H14 -> 30000 | I15: =I13*1000/I14 -> 36000 | J15: =J13*1000/J14 -> 42000 | K15: =K13*1000/K14 -> 42000 | L15: =L13*1000/L14 -> 42000 | ... S15: =S13*1000/S14 -> 42000 | T15: =S15 -> 42000 | U15: =T15 -> 42000 | V15: =U15 -> 42000 | W15: =V15 -> 42000 | X15: =W15 -> 42000 | Y15: =X15 -> 42000 | Z15: =Y15 -> 42000 | AA15: =Z15 -> 42000 | ... AC15: =AB15 -> 42000
B16: Increase in fodder production per hactare (MT) | E16: 40 | F16: 40 | G16: 40 | H16: 40 | I16: 40 | J16: 40 | K16: 40 | L16: 40 | M16: 40 | N16: 40 | O16: 40 | P16: 40 | Q16: 40 | R16: 40 | S16: 40 | T16: =S16 -> 40 | U16: =T16 -> 40 | V16: =U16 -> 40 | W16: =V16 -> 40 | X16: =W16 -> 40 | Y16: =X16 -> 40 | Z16: =Y16 -> 40 | AA16: =Z16 -> 40 | ... AC16: =AB16 -> 40
B17: Annual increase in fodder production (million MT) | E17: =E15*E16/1000000 -> 0.24 | F17: =F15*F16/1000000 -> 0.48 | G17: =G15*G16/1000000 -> 0.96 | H17: =H15*H16/1000000 -> 1.2 | I17: =I15*I16/1000000 -> 1.44 | J17: =J15*J16/1000000 -> 1.68 | K17: =K15*K16/1000000 -> 1.68 | L17: =L15*L16/1000000 -> 1.68 | ... S17: =S15*S16/1000000 -> 1.68 | T17: =S17 -> 1.68 | U17: =T17 -> 1.68 | V17: =U17 -> 1.68 | W17: =V17 -> 1.68 | X17: =W17 -> 1.68 | Y17: =X17 -> 1.68 | Z17: =Y17 -> 1.68 | AA17: =Z17 -> 1.68 | ... AC17: =AB17 -> 1.68
B18: Increase in milk production for every 10 Kg fodder (Kg) | E18: 1 | F18: 1 | G18: 1 | H18: 1 | I18: 1 | J18: 1 | K18: 1 | L18: 1 | M18: 1 | N18: 1 | O18: 1 | P18: 1 | Q18: 1 | R18: 1 | S18: 1 | T18: =S18 -> 1 | U18: =T18 -> 1 | V18: =U18 -> 1 | W18: =V18 -> 1 | X18: =W18 -> 1 | Y18: =X18 -> 1 | Z18: =Y18 -> 1 | AA18: =Z18 -> 1 | ... AC18: =AB18 -> 1
B19: Net increase in milk production in the year (million MT) | E19: =E17*E18/10 -> 0.024 | F19: =F17*F18/10 -> 0.048 | G19: =G17*G18/10 -> 0.096 | H19: =H17*H18/10 -> 0.12 | I19: =I17*I18/10 -> 0.144 | J19: =J17*J18/10 -> 0.168 | K19: =K17*K18/10 -> 0.168 | L19: =L17*L18/10 -> 0.168 | ... S19: =S17*S18/10 -> 0.168 | T19: =S19 -> 0.168 | U19: =T19 -> 0.168 | V19: =U19 -> 0.168 | W19: =V19 -> 0.168 | X19: =W19 -> 0.168 | Y19: =X19 -> 0.168 | Z19: =Y19 -> 0.168 | AA19: =Z19 -> 0.168 | ... AC19: =AB19 -> 0.168
B20: Net increase in milk production in the year ('000 Tonnes) | E20: =E19*1000 -> 24 | F20: =F19*1000 -> 48 | G20: =G19*1000 -> 96 | H20: =H19*1000 -> 120 | I20: =I19*1000 -> 144 | J20: =J19*1000 -> 168 | K20: =K19*1000 -> 168 | L20: =L19*1000 -> 168 | ... S20: =S19*1000 -> 168 | T20: =S20 -> 168 | U20: =T20 -> 168 | V20: =U20 -> 168 | W20: =V20 -> 168 | X20: =W20 -> 168 | Y20: =X20 -> 168 | Z20: =Y20 -> 168 | AA20: =Z20 -> 168 | ... AC20: =AB20 -> 168
A22: C | B22: Straw Densification Plants ( Nos.) | E22: 0 | F22: 1 | G22: 1 | H22: 2 | I22: 2 | J22: 2 | K22: =J22 -> 2 | L22: =K22 -> 2 | M22: =L22 -> 2 | N22: =M22 -> 2 | O22: =N22 -> 2 | P22: =O22 -> 2 | Q22: =P22 -> 2 | R22: =Q22 -> 2 | ... AC22: =AB22 -> 2
B23: Capacity of Straw Densification Plants (MTD) | E23: 40 | F23: 40 | G23: 40 | H23: 40 | I23: 40 | J23: 40 | K23: 40 | L23: 40 | M23: 40 | N23: 40 | O23: 40 | P23: 40 | Q23: 40 | R23: 40 | S23: 40 | T23: 40 | U23: 40 | V23: 40 | W23: 40 | X23: 40 | Y23: 40 | Z23: 40 | AA23: 40 | AB23: 40 | AC23: 40
B24: Anticipated Annual Production (MT) | E24: =E22*E23*300 -> 0 | F24: =F22*F23*300 -> 12000 | G24: =G22*G23*300 -> 12000 | H24: =H22*H23*300 -> 24000 | I24: =I22*I23*300 -> 24000 | J24: =J22*J23*300 -> 24000 | K24: =K22*K23*300 -> 24000 | L24: =L22*L23*300 -> 24000 | ... AC24: =AC22*AC23*300 -> 24000
A25: C | B25: Devt of permanent pasture & common grazing lands
B26: Live Fencing, Plantation, Perennial Grass Seeding, Land and Irrigation Development (Area to be covered) | E26: 400 | F26: 800 | G26: 1200 | H26: 1600 | I26: 2000 | J26: 2800 | K26: =J26 -> 2800 | L26: =K26 -> 2800 | M26: =L26 -> 2800 | N26: =M26 -> 2800 | O26: =N26 -> 2800 | P26: =O26 -> 2800 | Q26: =P26 -> 2800 | R26: =Q26 -> 2800 | ... AC26: =AB26 -> 2800
B27: Incremental Biomass (From 0.75 MT/ hect/yr to 5.75 MT/hect/yr) | E27: =E26*5 -> 2000 | F27: =F26*5 -> 4000 | G27: =G26*5 -> 6000 | H27: =H26*5 -> 8000 | I27: =I26*5 -> 10000 | J27: =J26*5 -> 14000 | K27: =J27 -> 14000 | L27: =K27 -> 14000 | M27: =L27 -> 14000 | N27: =M27 -> 14000 | O27: =N27 -> 14000 | P27: =O27 -> 14000 | Q27: =P27 -> 14000 | R27: =Q27 -> 14000 | ... AC27: =AB27 -> 14000
B28: Annual increase in fodder production (million MT) | E28: =E27/1000000 -> 0.002 | F28: =F27/1000000 -> 0.004 | G28: =G27/1000000 -> 0.006 | H28: =H27/1000000 -> 0.008 | I28: =I27/1000000 -> 0.01 | J28: =J27/1000000 -> 0.014 | K28: =J28 -> 0.014 | L28: =K28 -> 0.014 | M28: =L28 -> 0.014 | N28: =M28 -> 0.014 | O28: =N28 -> 0.014 | P28: =O28 -> 0.014 | Q28: =P28 -> 0.014 | R28: =Q28 -> 0.014 | ... AC28: =AB28 -> 0.014
B29: Increase in milk production for every 10 Kg fodder (Kg) | E29: 1 | F29: 1 | G29: 1 | H29: 1 | I29: 1 | J29: 1 | K29: =J29 -> 1 | L29: =K29 -> 1 | M29: =L29 -> 1 | N29: =M29 -> 1 | O29: =N29 -> 1 | P29: =O29 -> 1 | Q29: =P29 -> 1 | R29: =Q29 -> 1 | ... AC29: =AB29 -> 1
B30: Net increase in milk production in the year (million MT) | E30: =E28*E29/10 -> 0.0002 | F30: =F28*F29/10 -> 0.0004 | G30: =G28*G29/10 -> 0.0006 | H30: =H28*H29/10 -> 0.0008 | I30: =I28*I29/10 -> 0.001 | J30: =J28*J29/10 -> 0.0014 | K30: =J30 -> 0.0014 | L30: =K30 -> 0.0014 | M30: =L30 -> 0.0014 | N30: =M30 -> 0.0014 | O30: =N30 -> 0.0014 | P30: =O30 -> 0.0014 | Q30: =P30 -> 0.0014 | R30: =Q30 -> 0.0014 | ... AC30: =AB30 -> 0.0014
B31: Net increase in milk production in the year ('000 Tonnes) | E31: =E30*1000 -> 0.2 | F31: =F30*1000 -> 0.4 | G31: =G30*1000 -> 0.6 | H31: =H30*1000 -> 0.8 | I31: =I30*1000 -> 1 | J31: =J30*1000 -> 1.4 | K31: =K30*1000 -> 1.4 | L31: =L30*1000 -> 1.4 | ... S31: =S30*1000 -> 1.4 | T31: =S31 -> 1.4 | U31: =T31 -> 1.4 | V31: =U31 -> 1.4 | W31: =V31 -> 1.4 | X31: =W31 -> 1.4 | Y31: =X31 -> 1.4 | Z31: =Y31 -> 1.4 | AA31: =Z31 -> 1.4 | ... AC31: =AB31 -> 1.4
A32: D | B32: Organising Varietal Demonstrations (1/10 of Hect) | E32: 20000 | F32: 40000 | G32: 60000 | H32: 80000 | I32: 100000 | J32: 140000 | K32: =J32 -> 140000 | L32: =K32 -> 140000 | M32: =L32 -> 140000 | N32: =M32 -> 140000 | O32: =N32 -> 140000 | P32: =O32 -> 140000 | Q32: =P32 -> 140000 | R32: =Q32 -> 140000 | ... AC32: =AB32 -> 140000
B33: Villages covered under Varietal Demonstrations (nos.) | E33: =E32/4 -> 5000 | F33: =F32/4 -> 10000 | G33: =G32/4 -> 15000 | H33: =H32/4 -> 20000 | I33: =I32/4 -> 25000 | J33: =J32/4 -> 35000 | K33: =J33 -> 35000 | L33: =K33 -> 35000 | M33: =L33 -> 35000 | N33: =M33 -> 35000 | O33: =N33 -> 35000 | P33: =O33 -> 35000 | Q33: =P33 -> 35000 | R33: =Q33 -> 35000 | ... AC33: =AB33 -> 35000
B34: Villages covered under Varietal Demonstrations (nos.) | E34: =E32/10 -> 2000 | F34: =F32/10 -> 4000 | G34: =G32/10 -> 6000 | H34: =H32/10 -> 8000 | I34: =I32/10 -> 10000 | J34: =J32/10 -> 14000 | K34: =J34 -> 14000 | L34: =K34 -> 14000 | M34: =L34 -> 14000 | N34: =M34 -> 14000 | O34: =N34 -> 14000 | P34: =O34 -> 14000 | Q34: =P34 -> 14000 | R34: =Q34 -> 14000 | ... AC34: =AB34 -> 14000
B35: Increase in fodder production per hactare (MT) | E35: 40 | F35: 40 | G35: 40 | H35: 40 | I35: 40 | J35: 40 | K35: 40 | L35: =K35 -> 40 | M35: =L35 -> 40 | N35: =M35 -> 40 | O35: =N35 -> 40 | P35: =O35 -> 40 | Q35: =P35 -> 40 | R35: =Q35 -> 40 | S35: =R35 -> 40 | ... AC35: =AB35 -> 40
B36: Annual increase in fodder production (million MT) | E36: =E34*E35/1000000 -> 0.08 | F36: =F34*F35/1000000 -> 0.16 | G36: =G34*G35/1000000 -> 0.24 | H36: =H34*H35/1000000 -> 0.32 | I36: =I34*I35/1000000 -> 0.4 | J36: =J34*J35/1000000 -> 0.56 | K36: =K34*K35/1000000 -> 0.56 | L36: =K36 -> 0.56 | M36: =L36 -> 0.56 | N36: =M36 -> 0.56 | O36: =N36 -> 0.56 | P36: =O36 -> 0.56 | Q36: =P36 -> 0.56 | R36: =Q36 -> 0.56 | S36: =R36 -> 0.56 | ... AC36: =AB36 -> 0.56
B37: Increase in milk production for every 10 Kg fodder (Kg) | E37: 1 | F37: 1 | G37: 1 | H37: 1 | I37: 1 | J37: 1 | K37: =J37 -> 1 | L37: =K37 -> 1 | M37: =L37 -> 1 | N37: =M37 -> 1 | O37: =N37 -> 1 | P37: =O37 -> 1 | Q37: =P37 -> 1 | R37: =Q37 -> 1 | ... AC37: =AB37 -> 1
B38: Net increase in milk production in the year (million MT) | E38: =E36*E37/10 -> 0.008 | F38: =F36*F37/10 -> 0.016 | G38: =G36*G37/10 -> 0.024 | H38: =H36*H37/10 -> 0.032 | I38: =I36*I37/10 -> 0.04 | J38: =J36*J37/10 -> 0.056 | K38: =J38 -> 0.056 | L38: =K38 -> 0.056 | M38: =L38 -> 0.056 | N38: =M38 -> 0.056 | O38: =N38 -> 0.056 | P38: =O38 -> 0.056 | Q38: =P38 -> 0.056 | R38: =Q38 -> 0.056 | ... AC38: =AB38 -> 0.056
B39: Net increase in milk production in the year ('000 Tonnes) | E39: =E38*1000 -> 8 | F39: =F38*1000 -> 16 | G39: =G38*1000 -> 24 | H39: =H38*1000 -> 32 | I39: =I38*1000 -> 40 | J39: =J38*1000 -> 56 | K39: =K38*1000 -> 56 | L39: =L38*1000 -> 56 | ... S39: =S38*1000 -> 56 | T39: =S39 -> 56 | U39: =T39 -> 56 | V39: =U39 -> 56 | W39: =V39 -> 56 | X39: =W39 -> 56 | Y39: =X39 -> 56 | Z39: =Y39 -> 56 | AA39: =Z39 -> 56 | ... AC39: =AB39 -> 56
E40: =+E6 -> 366000 | F40: =+F6-E6 -> 375000 | G40: =+G6-F6 -> 447000 | H40: =+H6-G6 -> 630000 | I40: =+I6-H6 -> 574800 | J40: =+J6-I6 -> 326400 | K40: =+K6-J6 -> 0 | L40: =+L6-K6 -> 0
B41: Weighted average milk yield, Kg/day | C41: =+C59*1.03 -> 4.6587415
B42: Milk Productivity with RBP Intervention (Kg/day/animal), Incremental | C42: =+C41*E59 -> 0.46587415
B43: Milk Poduction with RBP intervention (Million tonnes), Incremental | C43: Million Tonnes | E43: 0 | F43: =$C$42*E6*365/1000000000 -> 0.062236128 | G43: =$C$42*F6*365/1000000000 -> 0.12600265 | H43: =$C$42*G6*365/1000000000 -> 0.20201235 | I43: =$C$42*H6*365/1000000000 -> 0.30914011 | J43: =$C$42*I6*365/1000000000 -> 0.40688144 | K43: =$C$42*J6*365/1000000000 -> 0.46238382 | L43: =$C$42*K6*365/1000000000 -> 0.46238382 | M43: =$C$42*L6*365/1000000000 -> 0.46238382 | ... AC43: =$C$42*AB6*365/1000000000 -> 0.46238382
B44: Quantity of Additional Fat Produced with RBP (Million tonnes) | C44: ='Feed and Fodder'!S4 -> 0.0025 | E44: =$C$44*E43 -> 0 | F44: =$C$44*F43 -> 0.00015559032 | G44: =$C$44*G43 -> 0.00031500663 | H44: =$C$44*H43 -> 0.00050503087 | I44: =$C$44*I43 -> 0.00077285027 | J44: =$C$44*J43 -> 0.0010172036 | K44: =$C$44*K43 -> 0.0011559596 | L44: =$C$44*L43 -> 0.0011559596 | ... AC44: =$C$44*AC43 -> 0.0011559596
B45: Reduction in Feeding Cost | C45: Million Rupees | E45: 0 | F45: =+$C$71*$C$41*E6*365/1000000 -> 371.57019 | G45: =+$C$71*$C$41*F6*365/1000000 -> 752.27736 | H45: =+$C$71*$C$41*G6*365/1000000 -> 1206.0803 | I45: =+$C$71*$C$41*H6*365/1000000 -> 1845.6683 | J45: =+$C$71*$C$41*I6*365/1000000 -> 2429.2163 | K45: =+$C$71*$C$41*J6*365/1000000 -> 2760.5838 | L45: =+$C$71*$C$41*K6*365/1000000 -> 2760.5838 | M45: =+$C$71*$C$41*L6*365/1000000 -> 2760.5838 | ... AC45: =+$C$71*$C$41*AB6*365/1000000 -> 2760.5838
B47: Reduction in Methane Emissions (CER units per annum) | C47: ='Feed and Fodder'!D33 -> 0.16453421 | E47: 0 | F47: =$C$47*E6 -> 60219.522 | G47: =$C$47*F6 -> 121919.85 | H47: =$C$47*G6 -> 195466.64 | I47: =$C$47*H6 -> 299123.2 | J47: =$C$47*I6 -> 393697.46 | K47: =$C$47*J6 -> 447401.43 | L47: =$C$47*K6 -> 447401.43 | M47: =$C$47*L6 -> 447401.43 | ... AC47: =$C$47*AB6 -> 447401.43
B48: Benefit due to reduction in Methane Emissions ( Rs million per annum) | C48: ='Feed and Fodder'!C34 -> 740 | E48: =E47*$C$48/1000000 -> 0 | F48: =F47*$C$48/1000000 -> 44.562446 | G48: =G47*$C$48/1000000 -> 90.22069 | H48: =H47*$C$48/1000000 -> 144.64532 | I48: =I47*$C$48/1000000 -> 221.35117 | J48: =J47*$C$48/1000000 -> 291.33612 | K48: =K47*$C$48/1000000 -> 331.07706 | L48: =L47*$C$48/1000000 -> 331.07706 | ... AC48: =AC47*$C$48/1000000 -> 331.07706
B50: Benefit due to increase in milk productivity (Rs Million pe annum) | E50: =+E43*$G$62 -> 0 | F50: =+F43*$G$62 -> 224.69631 | G50: =+G43*$G$62 -> 454.91793 | H50: =+H43*$G$62 -> 729.34211 | I50: =+I43*$G$62 -> 1116.1144 | J50: =+J43*$G$62 -> 1468.9982 | K50: =+K43*$G$62 -> 1669.3831 | L50: =+L43*$G$62 -> 1669.3831 | ... AC50: =+AC43*$G$62 -> 1669.3831
B52: Total Benefits from RBP Programme | E52: =+SUM(E45,E48,E50) -> 0 | F52: =+SUM(F45,F48,F50) -> 640.82894 | G52: =+SUM(G45,G48,G50) -> 1297.416 | H52: =+SUM(H45,H48,H50) -> 2080.0677 | I52: =+SUM(I45,I48,I50) -> 3183.1339 | J52: =+SUM(J45,J48,J50) -> 4189.5505 | K52: =+SUM(K45,K48,K50) -> 4761.0439 | L52: =+SUM(L45,L48,L50) -> 4761.0439 | ... AC52: =+SUM(AC45,AC48,AC50) -> 4761.0439
B55: Assumptions :
J56: =+C57*C42 -> 170.04406
B57: Number of days in lactation considered | C57: 365 | G57: Incremental | J57: =+J56*1.03 -> 175.14539 | K57: =+J57/1000 -> 0.17514539
G58: Lactn Yield, L | J58: =+J57*J6 -> 4.7625534e+08 | K58: =+K57*2.94 -> 0.51492744
B59: Average Mik yield ( l/day) | C59: ='Feed and Fodder (F) Zone.2'!$C$59 -> 4.52305 | E59: ='Feed and Fodder (F) Zone.1'!$E$59 -> 0.1 | G59: =+C59*C57*E59 -> 165.09132
C60: l/day | E60: Proportion Considered
B61: Indigenous cows | C61: 2.136 | E61: 0.35 | G61: Ecomomic Gross Margin | I61: Rs/MT
B62: Cross Breds | C62: 6.869 | E62: 0.35 | G62: 3610.3838
B63: buffaloes | C63: 4.571 | E63: ='Feed and Fodder'!C25 -> 0.3
G65: Economic Production Cost | I65: Rs/Kg
B66: Unit Prodn Cost, Rs/Kg | C66: =+G66 -> 17.058084 | G66: 17.058084
B67: Feed and Fodder Cost, % | C67: 0.7
B68: Feed and Fodder Cost, Rs/Kg | C68: =+C66*C67 -> 11.940659
B70: Reduction in Feed and Fodder Cost, % | C70: 0.05
B71: Savings in Feed and Fodder Cost, Rs/Kg | C71: =+C68*C70 -> 0.59703295
C75: 1 | E75: Yr-1 | F75: Yr-2 | G75: Yr-3 | H75: Yr-4 | I75: Yr-5 | J75: Yr-6 | K75: Yr-7 | L75: Yr-8 | M75: Yr-9 | N75: Yr-10 | O75: Yr-11 | P75: Yr-12 | Q75: Yr-13 | R75: Yr-14 | S75: Yr-15 | T75: Yr-16 | U75: Yr-17 | V75: Yr-18 | W75: Yr-19 | X75: Yr-20 | Y75: Yr-21 | Z75: Yr-22 | AA75: Yr-23 | AB75: Yr-24 | AC75: Yr-25 | AD75: Yr-26
B76: For EFA Analysis | C76: Adopters | E76: 0 | F76: 0 | G76: 0.25 | H76: 0.5 | I76: 0.75 | J76: 1 | K76: 1 | L76: 1 | M76: 1 | N76: 1 | O76: 1 | P76: 1 | Q76: 1 | R76: 1 | S76: 1 | T76: 1 | U76: 1 | V76: 1 | W76: 1 | X76: 1 | Y76: 1 | Z76: 1 | AA76: 1 | AB76: 1 | AC76: 1 | AD76: 1
C77: 0.05 | E77: =+$C77*E76*$C$75 -> 0 | F77: =+$C77*F76*$C$75 -> 0 | G77: =+$C77*G76*$C$75 -> 0.0125 | H77: =+$C77*H76*$C$75 -> 0.025 | I77: =+$C77*I76*$C$75 -> 0.0375 | J77: =+$C77*J76*$C$75 -> 0.05 | K77: =+$C77*K76*$C$75 -> 0.05 | L77: =+$C77*L76*$C$75 -> 0.05 | ... AD77: =+$C77*AD76*$C$75 -> 0.05
C78: 0.1 | F78: =+$C78*E76*$C$75 -> 0 | G78: =+$C78*F76*$C$75 -> 0 | H78: =+$C78*G76*$C$75 -> 0.025 | I78: =+$C78*H76*$C$75 -> 0.05 | J78: =+$C78*I76*$C$75 -> 0.075 | K78: =+$C78*J76*$C$75 -> 0.1 | L78: =+$C78*K76*$C$75 -> 0.1 | M78: =+$C78*L76*$C$75 -> 0.1 | ... AD78: =+$C78*AC76*$C$75 -> 0.1
C79: 0.2 | G79: =+$C79*E76*$C$75 -> 0 | H79: =+$C79*F76*$C$75 -> 0 | I79: =+$C79*G76*$C$75 -> 0.05 | J79: =+$C79*H76*$C$75 -> 0.1 | K79: =+$C79*I76*$C$75 -> 0.15 | L79: =+$C79*J76*$C$75 -> 0.2 | M79: =+$C79*K76*$C$75 -> 0.2 | N79: =+$C79*L76*$C$75 -> 0.2 | ... AD79: =+$C79*AB76*$C$75 -> 0.2
C80: 0.25 | H80: =+$C80*E76*$C$75 -> 0 | I80: =+$C80*F76*$C$75 -> 0 | J80: =+$C80*G76*$C$75 -> 0.0625 | K80: =+$C80*H76*$C$75 -> 0.125 | L80: =+$C80*I76*$C$75 -> 0.1875 | M80: =+$C80*J76*$C$75 -> 0.25 | N80: =+$C80*K76*$C$75 -> 0.25 | O80: =+$C80*L76*$C$75 -> 0.25 | ... AD80: =+$C80*AA76*$C$75 -> 0.25
C81: 0.3 | I81: =+$C81*E76*$C$75 -> 0 | J81: =+$C81*F76*$C$75 -> 0 | K81: =+$C81*G76*$C$75 -> 0.075 | L81: =+$C81*H76*$C$75 -> 0.15 | M81: =+$C81*I76*$C$75 -> 0.225 | N81: =+$C81*J76*$C$75 -> 0.3 | O81: =+$C81*K76*$C$75 -> 0.3 | P81: =+$C81*L76*$C$75 -> 0.3 | ... AD81: =+$C81*Z76*$C$75 -> 0.3
C82: 0.1 | J82: =+$C82*E76*$C$75 -> 0 | K82: =+$C82*F76*$C$75 -> 0 | L82: =+$C82*G76*$C$75 -> 0.025 | M82: =+$C82*H76*$C$75 -> 0.05 | N82: =+$C82*I76*$C$75 -> 0.075 | O82: =+$C82*J76*$C$75 -> 0.1 | P82: =+$C82*K76*$C$75 -> 0.1 | Q82: =+$C82*L76*$C$75 -> 0.1 | ... AD82: =+$C82*Y76*$C$75 -> 0.1
C83: =+SUM(C77:C82) -> 1 | E83: =SUM(E77:E82) -> 0 | F83: =SUM(F77:F82) -> 0 | G83: =SUM(G77:G82) -> 0.0125 | H83: =SUM(H77:H82) -> 0.05 | I83: =SUM(I77:I82) -> 0.1375 | J83: =SUM(J77:J82) -> 0.2875 | K83: =SUM(K77:K82) -> 0.5 | L83: =SUM(L77:L82) -> 0.7125 | ... AD83: =SUM(AD77:AD82) -> 1
B84: Zone-2
C85: 0.5
B86: =+B45 -> Reduction in Feeding Cost | E86: =+E$83*E45*$C$85 -> 0 | F86: =+F$83*F45*$C$85 -> 0 | G86: =+G$83*G45*$C$85 -> 4.7017335 | H86: =+H$83*H45*$C$85 -> 30.152007 | I86: =+I$83*I45*$C$85 -> 126.8897 | J86: =+J$83*J45*$C$85 -> 349.19984 | K86: =+K$83*K45*$C$85 -> 690.14595 | L86: =+L$83*L45*$C$85 -> 983.45797 | ... AD86: =+AD$83*AD45*$C$85 -> 0 | AF86: =+AC86/SUM($AC$86:$AC$90) -> 0.57982742
B88: =+B48 -> Benefit due to reduction in Methane Emissions ( Rs million per annum) | E88: =+E$83*E48*$C$85 -> 0 | F88: =+F$83*F48*$C$85 -> 0 | G88: =+G$83*G48*$C$85 -> 0.56387931 | H88: =+H$83*H48*$C$85 -> 3.6161329 | I88: =+I$83*I48*$C$85 -> 15.217893 | J88: =+J$83*J48*$C$85 -> 41.879568 | K88: =+K$83*K48*$C$85 -> 82.769265 | L88: =+L$83*L48*$C$85 -> 117.9462 | ... AD88: =+AD$83*AD48*$C$85 -> 0 | AF88: =+AC88/SUM($AC$86:$AC$90) -> 0.069538754
B90: =+B50 -> Benefit due to increase in milk productivity (Rs Million pe annum) | E90: =+E$83*E50*$C$85 -> 0 | F90: =+F$83*F50*$C$85 -> 0 | G90: =+G$83*G50*$C$85 -> 2.8432371 | H90: =+H$83*H50*$C$85 -> 18.233553 | I90: =+I$83*I50*$C$85 -> 76.732868 | J90: =+J$83*J50*$C$85 -> 211.16848 | K90: =+K$83*K50*$C$85 -> 417.34576 | L90: =+L$83*L50*$C$85 -> 594.71771 | ... AD90: =+AD$83*AD50*$C$85 -> 0 | AF90: =+AC90/SUM($AC$86:$AC$90) -> 0.35063383
B93: Milk Prodn | C93: Million Tonnes | D93: Zone-2 | E93: =+E43*E83*$C$85 -> 0 | F93: =+F43*F83*$C$85 -> 0 | G93: =+G43*G83*$C$85 -> 0.00078751657 | H93: =+H43*H83*$C$85 -> 0.0050503087 | I93: =+I43*I83*$C$85 -> 0.021253383 | J93: =+J43*J83*$C$85 -> 0.058489207 | K93: =+K43*K83*$C$85 -> 0.11559596 | L93: =+L43*L83*$C$85 -> 0.16472424 | ... AD93: =+AD43*AD83*$C$85 -> 0
D94: Zone-1 | E94: =+'Feed and Fodder (E) Zone.1'!E43*'Feed and Fodder (E) Zone.1'!$C$85*'Feed and Fodder (E) Zone.1'!E83 -> 0 | F94: =+'Feed and Fodder (E) Zone.1'!F43*'Feed and Fodder (E) Zone.1'!$C$85*'Feed and Fodder (E) Zone.1'!F83 -> 0 | G94: =+'Feed and Fodder (E) Zone.1'!G43*'Feed and Fodder (E) Zone.1'!$C$85*'Feed and Fodder (E) Zone.1'!G83 -> 0.00078751657 | H94: =+'Feed and Fodder (E) Zone.1'!H43*'Feed and Fodder (E) Zone.1'!$C$85*'Feed and Fodder (E) Zone.1'!H83 -> 0.0050503087 | I94: =+'Feed and Fodder (E) Zone.1'!I43*'Feed and Fodder (E) Zone.1'!$C$85*'Feed and Fodder (E) Zone.1'!I83 -> 0.021253383 | J94: =+'Feed and Fodder (E) Zone.1'!J43*'Feed and Fodder (E) Zone.1'!$C$85*'Feed and Fodder (E) Zone.1'!J83 -> 0.058489207 | K94: =+'Feed and Fodder (E) Zone.1'!K43*'Feed and Fodder (E) Zone.1'!$C$85*'Feed and Fodder (E) Zone.1'!K83 -> 0.11559596 | L94: =+'Feed and Fodder (E) Zone.1'!L43*'Feed and Fodder (E) Zone.1'!$C$85*'Feed and Fodder (E) Zone.1'!L83 -> 0.16472424 | ... AD94: =+'Feed and Fodder (E) Zone.1'!AD43*'Feed and Fodder (E) Zone.1'!$C$85*'Feed and Fodder (E) Zone.1'!AD83 -> 0
E96: =+SUM(E93:E94) -> 0 | F96: =+SUM(F93:F94) -> 0 | G96: =+SUM(G93:G94) -> 0.0015750331 | H96: =+SUM(H93:H94) -> 0.010100617 | I96: =+SUM(I93:I94) -> 0.042506765 | J96: =+SUM(J93:J94) -> 0.11697841 | K96: =+SUM(K93:K94) -> 0.23119191 | L96: =+SUM(L93:L94) -> 0.32944847 | ... AD96: =+SUM(AD93:AD94) -> 0
B98: Feed Cost | E98: ='Feed and Fodder (F) Zone.1'!$E$59 -> 0.1 | F98: =+F93/F96 -> #DIV/0! | G98: =+G93/G96 -> 0.5 | H98: =+H93/H96 -> 0.5 | I98: =+I93/I96 -> 0.5 | J98: =+J93/J96 -> 0.5 | K98: =+K93/K96 -> 0.5 | L98: =+L93/L96 -> 0.5 | M98: =+M93/M96 -> 0.5 | ... AD98: =+AD93/AD96 -> #DIV/0!
E99: =+E94/E96 -> #DIV/0! | F99: =+F94/F96 -> #DIV/0! | G99: =+G94/G96 -> 0.5 | H99: =+H94/H96 -> 0.5 | I99: =+I94/I96 -> 0.5 | J99: =+J94/J96 -> 0.5 | K99: =+K94/K96 -> 0.5 | L99: =+L94/L96 -> 0.5 | ... AD99: =+AD94/AD96 -> #DIV/0!
O101: =+O96*3064 -> 1416.744
